Workbook
Name Activité_projet: 'Liste Activites'!$C$2:$C$115
Name base: Organisation!$B$2:$D$47
Name code: Organisation!$A$2:$A$47
Name code_unité: Organisation!$B$2:$B$47
Name contrat: 'autres ldv'!$J$48:$J$55
Name conv_is: 'autres ldv'!#REF!
Name convention: 'autres ldv'!$A$11:$A$12
Name departement: Organisation!$A$2:$D$47
Name FI: 'autres ldv'!$B$30
Name FP: 'autres ldv'!$B$31
Name FR: 'autres ldv'!$B$32
Name Géo: 'Liste Géo'!$C$2:$C$260
Name montant: 'autres ldv'!$A$19:$C$21
Name oui_non: 'autres ldv'!$A$15:$A$16
Name pays: Pays!$A$2:$A$247
Name PaysRatt: Pays!$A$2:$A$6
Name PI: 'autres ldv'!$B$28
Name PP: 'autres ldv'!$B$29
Name Structure: '[1]Liste Structure'!$C$2:$C$128
Name Structure: '[1]Liste Structure'!$C$2:$C$128
Name Structure: 'Liste Structure'!$C$2:$C$116
Name transport: 'autres ldv'!$A$6:$A$10
Name type: 'autres ldv'!$A$4:$A$4
Name unite: Organisation!$C$2:$C$47
Name vehicule: 'autres ldv'!$A$19:$A$21
Name vehicule_m: 'autres ldv'!$A$19:$C$21

Sheet Aide à la saisie
A1: Recommandations
A2: Les améliorations ci-dessous reposent sur de nombreuses formules de calcul liées à des tables de paramètres régulièrement mises à jour
A3: (forfaits, plafonds, coefficients d'éloignement, indemnités kilométriques, …).
A6: 1 - Bien renseigner les 3 axes : Structure (UR/Sce), Projet/Activité et Géographique (pays de la mission)
A7: Structure et Géographique sont remplis en automatique (mais modifiables) selon votre saisie
A8: Projet/activité est à saisir sous la forme :
F10: les activités: | G10: leurs codes commencent par un A sur 10 caractères maximum
F11: les prospects: | G11: leurs codes commencent par un P sur 10 caractères maximum
F12: les conventions | G12: leurs codes commencent par un C sur 10 caractères maximum
A14: 2 - L'ODM et la NDF sont toujours liés : toute saisie dans l'ODM utile pour la liquidation est automatiquement reportée dans la NDF
A15: Ces éléments reportés peuvent bien sûr être corrigés dans la NDF au moment de la liquidation
A17: L'ODM et la NDF sont liés par le N°d'ODM qui se compose :
A18: - du code UR/service
A19: - du millésime, déduit de la date de départ en mission
A20: - du n°d'ordre ou chrono, compris entre 1 et 999 sur 3 caractères maximum
A21: - du code "Gd Projet", facultatif sur 2 caractères, pour les missions concernant des Grands Projets
A23: 3 - Une nouvelle notion, le pays principal de la mission, se remplit en automatique selon le plus grand nombre de jours calculé dans l'itinéraire. Il reste cependant modifiable
A25: 4 - Renseigner dans l'ODM toutes les cellules en bleu du budget prévisionnel
A27: 5 - Le calcul de l'IS se fait en automatique.
A28: Pour que les calculs automatiques fonctionnent, il faut renseigner tous les pays et toutes les dates de l'itinéraire de la mission
A29: ainsi que les informations concernant le salarié : contrat de travail, pays d'affectation et pays de rattachement.
... A34: 7 - Pour traiter l'ODM, le G2M a besoin :
D35: - du formulaire ODM/NDF en version Excel et en version pdf avec toutes les signatures apposées (salarié et responsable hiérarchique)
D36: - L'onglet "ODM" doit être dument complété : structure, projet/activité, géographie, n°d'ordre…
A38: 8 - Pour traiter la NDF, le G2M a besoin :
D39: - du formulaire ODM/NDF en version Excel (le même qui a servi à établir l'ODM) L'onglet "NDF" doit être dument complété.
D40: - des documents ODM et NDF en version pdf avec toutes les signatures apposées (salarié et responsable hiérarchique)
D41: - tous les justificatifs scannés, lisibles et numérotés, y compris les titres de transport aller/retour, le tout en version pdf.
A44: 9 - Transmettre tous les documents par mail à l'adresse générique : g2m-missions@cirad.fr
A45: Important : afin de permettre un dispatching automatique vers votre gestionnaire G2M, préciser le N° d'ODM au format AGORA dans l'objet du mail
A46: en respectant : N°ODM - NOM Prénom du missionnaire - Pays principal de la mission (exemple: C11200-20-005 - DURAND Cedric - Brésil).
A47: Le N° d'ODM au format AGORA est l'élément indispensable. Les autres mentions sont conseillées pour améliorer la lisibilité et la recherche des mails
A49: Pour la fluidité du traitement des documents :
A50: Le formulaire DCAF est désormais doté de deux onglets techniques AgoraODM et AgoraNDF inaccessibles à la saisie.
A51: Ces onglets techniques se documentent automatiquement à partir des informations saisies dans les autres onglets
A52: Après validation du G2M, ils sont interfacés pour intégration dans le logiciel QUALIAC et comptabilisation instantanée des frais
A54: Ces onglets techniques sont sujets à modifications tout au long de l'année en fonction des correctifs qui seront apportés au logiciel QUALIAC.
A55: C'est pourquoi il est indispensable de toujours repartir de la version vierge des formulaires Excel qui sont à votre disposition sur l'Intranet DCAF
A56: https://intranet-dcaf.cirad.fr/les-formulaires
A58: Comment solder un trop perçu d'avance auprès de Compta Missions Paris :
A60: En cas de trop perçu (avance supérieure aux frais engagés), le salarié droit adresser son remboursement :
F62: - par virement en utilisant le RIB ci-dessous
F63: en précisant son numéro de matricule et le numéro de l'ODM

Sheet ODM
E2: DESCRIPTION ET BUDGET DE LA MISSION | Q2: Formulaire DCAF
Q3: 24/01/2024
B4: N°d'ODM | C4: N°d'ODM | D4: Dpt. | F4: UR / Service | N4: Année | P4: N°Ordre | R4: Gd. Projet (2c)
A5: =W5 -> A10821-24-111 | D5: =IF(ISNA(VLOOKUP(LEFT(F5,1),'Liste Structure'!H2:I5,2,FALSE)),"",VLOOKUP(LEFT(F5,1),'Liste Structure'!H2:I5,2,FALSE)) -> Bios | F5: A10821-AGAP - PhenoMEn | N5: =IF(N16="","",YEAR(N16)) -> 2024 | P5: 111 | W5: =IF(ISNA(INDEX('Liste Structure'!A2:D129,MATCH(ODM!F5,'Liste Structure'!C2:C129,0),1)&"-"&P5),"",INDEX('Liste Structure'!A2:D129,MATCH(ODM!F5,'Liste Structure'!C2:C129,0),1)&"-"&RIGHT(N5,2)&"-"&REPT("0",(3-LEN(P5)))&P5&LEFT(R5,2)) -> A10821-24-111
B7: Matricule | D7: 30392 | H7: Type contrat : | J7: Doctorant Cirad | V7: Type contrat | W7: =IF(ISBLANK(J7),"",VLOOKUP(J7,'autres ldv'!J47:M62,4,FALSE)) -> ALLR
B9: Nom : | D9: BRAUD | L9: Prénom : | M9: Oriane
B11: Pays d'affectation : | F11: FRANCE MÉTROPOLITAINE | N11: Pays de rattachement : | P11: FRANCE MÉTROPOLITAINE
C13: Objet : | D13: Rencontre de collaborateurs dans le projet IntercropValuES
B15: Itinéraire | D15: Pays | H15: Ville | L15: Date arrivée | N15: Date départ | P15: Mission Longue Durée : | W15: Nb j missions | X15: Coef IS | Y15: IS hors charge | AA15: Perdiem | AC15: Pays
B16: Départ | D16: FRANCE MÉTROPOLITAINE | H16: Montpellier | N16: 45345 | Q16: =IF(F11<>P11,"NON",IF(Q20>=91,"OUI","NON")) -> NON
B17: Pays visité n°1 | D17: FRANCE MÉTROPOLITAINE | H17: Paris | L17: 45345 | N17: 45348 | W17: =IF(D17="","",IF(ODM!L18="",ODM!L23-ODM!N16+1,ODM!N17-ODM!N16+1)) -> 4 | X17: =IF(D17="","",IF($F$11<>$P$11,0,IF($D17=$F$11,0,IF(VLOOKUP($W$7,'autres ldv'!I$47:K$58,3,FALSE)="Non",0,VLOOKUP($D17,Pays!$A$1:$M$261,VLOOKUP($P$11,Pays!$A$1:$N$6,14,FALSE),FALSE))))) -> 0 | Y17: =IF($D17="","",IF($W$7="ALLR",IF($F$11="France métropolitaine",W17*X17*'autres ldv'!$B$39/30,W17*X17*'autres ldv'!$B$40/30),W17*X17*'autres ldv'!$B$37*'autres ldv'!$B$38/30)) -> 0 | AA17: =IF(D17="","",W17*VLOOKUP(UPPER(D17),Pays!A$2:M$253,11,FALSE)) -> 472 | AC17: =IF(D17="","",D17) -> FRANCE MÉTROPOLITAINE | AF17: =IFERROR(VLOOKUP(MAX(W17:W22),W17:AC22,7,FALSE),"") -> FRANCE MÉTROPOLITAINE
B18: Pays visité n°2 | D18: PAYS-BAS | H18: Wageningen | L18: 45348 | N18: 45351 | P18: Nombre de jours de mission hors congés | W18: =IF(D18="","",IF(ODM!L19="",IF(ODM!L$23-ODM!N17=0,1,ODM!L$23-ODM!N17),IF(ODM!N18-ODM!N17=0,1,ODM!N18-ODM!N17))) -> 3 | X18: =IF(D18="","",IF($F$11<>$P$11,0,IF($D18=$F$11,0,IF(VLOOKUP($W$7,'autres ldv'!I$47:K$58,3,FALSE)="Non",0,VLOOKUP($D18,Pays!$A$1:$M$261,VLOOKUP($P$11,Pays!$A$1:$N$6,14,FALSE),FALSE))))) -> 0 | Y18: =IF($D18="","",IF($W$7="ALLR",IF($F$11="France métropolitaine",W18*X18*'autres ldv'!$B$39/30,W18*X18*'autres ldv'!$B$40/30),W18*X18*'autres ldv'!$B$37*'autres ldv'!$B$38/30)) -> 0 | AA18: =IF(D18="","",W18*VLOOKUP(UPPER(D18),Pays!A$2:M$253,11,FALSE)) -> 270 | AC18: =IF(D18="","",D18) -> PAYS-BAS
B19: Pays visité n°3 | W19: =IF(D19="","",IF(ODM!L20="",IF(ODM!L$23-ODM!N18=0,1,ODM!L$23-ODM!N18),IF(ODM!N19-ODM!N18=0,1,ODM!N19-ODM!N18))) | X19: =IF(D19="","",IF($F$11<>$P$11,0,IF($D19=$F$11,0,IF(VLOOKUP($W$7,'autres ldv'!I$47:K$58,3,FALSE)="Non",0,VLOOKUP($D19,Pays!$A$1:$M$261,VLOOKUP($P$11,Pays!$A$1:$N$6,14,FALSE),FALSE))))) | Y19: =IF($D19="","",IF($W$7="ALLR",IF($F$11="France métropolitaine",W19*X19*'autres ldv'!$B$39/30,W19*X19*'autres ldv'!$B$40/30),W19*X19*'autres ldv'!$B$37*'autres ldv'!$B$38/30)) | AA19: =IF(D19="","",W19*VLOOKUP(UPPER(D19),Pays!A$2:M$253,11,FALSE)) | AC19: =IF(D19="","",D19)
B20: Pays visité n°4 | Q20: =IF(N16="",0,((L23-N16+1)-Q25)) -> 5 | W20: =IF(D20="","",IF(ODM!L21="",IF(ODM!L$23-ODM!N19=0,1,ODM!L$23-ODM!N19),IF(ODM!N20-ODM!N19=0,1,ODM!N20-ODM!N19))) | X20: =IF(D20="","",IF($F$11<>$P$11,0,IF($D20=$F$11,0,IF(VLOOKUP($W$7,'autres ldv'!I$47:K$58,3,FALSE)="Non",0,VLOOKUP($D20,Pays!$A$1:$M$261,VLOOKUP($P$11,Pays!$A$1:$N$6,14,FALSE),FALSE))))) | Y20: =IF($D20="","",IF($W$7="ALLR",IF($F$11="France métropolitaine",W20*X20*'autres ldv'!$B$39/30,W20*X20*'autres ldv'!$B$40/30),W20*X20*'autres ldv'!$B$37*'autres ldv'!$B$38/30)) | AA20: =IF(D20="","",W20*VLOOKUP(UPPER(D20),Pays!A$2:M$253,11,FALSE)) | AC20: =IF(D20="","",D20)
B21: Pays visité n°5 | W21: =IF(D21="","",IF(ODM!L22="",IF(ODM!L$23-ODM!N20=0,1,ODM!L$23-ODM!N20),IF(ODM!N21-ODM!N20=0,1,ODM!N21-ODM!N20))) | X21: =IF(D21="","",IF($F$11<>$P$11,0,IF($D21=$F$11,0,IF(VLOOKUP($W$7,'autres ldv'!I$47:K$58,3,FALSE)="Non",0,VLOOKUP($D21,Pays!$A$1:$M$261,VLOOKUP($P$11,Pays!$A$1:$N$6,14,FALSE),FALSE))))) | Y21: =IF($D21="","",IF($W$7="ALLR",IF($F$11="France métropolitaine",W21*X21*'autres ldv'!$B$39/30,W21*X21*'autres ldv'!$B$40/30),W21*X21*'autres ldv'!$B$37*'autres ldv'!$B$38/30)) | AA21: =IF(D21="","",W21*VLOOKUP(UPPER(D21),Pays!A$2:M$253,11,FALSE)) | AC21: =IF(D21="","",D21)
B22: Pays visité n°6 | P22: Nombre de jours de congés pendant la mission | W22: =IF(D22="","",IF(ODM!L23="",IF(ODM!L$23-ODM!N21=0,1,ODM!L$23-ODM!N21),IF(ODM!N22-ODM!N21=0,1,ODM!N22-ODM!N21))) | X22: =IF(D22="","",IF($F$11<>$P$11,0,IF($D22=$F$11,0,IF(VLOOKUP($W$7,'autres ldv'!I$47:K$58,3,FALSE)="Non",0,VLOOKUP($D22,Pays!$A$1:$M$261,VLOOKUP($P$11,Pays!$A$1:$N$6,14,FALSE),FALSE))))) | Y22: =IF($D22="","",IF($W$7="ALLR",IF($F$11="France métropolitaine",W22*X22*'autres ldv'!$B$39/30,W22*X22*'autres ldv'!$B$40/30),W22*X22*'autres ldv'!$B$37*'autres ldv'!$B$38/30)) | AA22: =IF(D22="","",W22*VLOOKUP(UPPER(D22),Pays!A$2:M$253,11,FALSE)) | AC22: =IF(D22="","",D22)
B23: Retour | D23: FRANCE MÉTROPOLITAINE | H23: Paris | L23: 45351 | X23: IS hors charge et congés déduites | Y23: =IFERROR(SUM(Y17:Y22)*((ODM!$L23-ODM!$N16+1)-ODM!$Q25)/(ODM!$L23-ODM!$N16+1),0) -> 0 | AA23: =IFERROR(SUM(AA17:AA22)*((ODM!$L23-ODM!$N16+1)-ODM!$Q25)/(ODM!$L23-ODM!$N16+1),0) -> 530 | AB23: Perdiem moyen congés déduites
B25: Congés du : | D25: 45346 | F25: au : | G25: 45347 | I25: et du : | L25: au : | Q25: =IF(AND(D25="",J25=""),0,'autres ldv'!B2+'autres ldv'!B3) -> 2 | X25: IS avec charge et congés déduites | Y25: =IFERROR(SUM(Y17:Y22)*(1+'autres ldv'!B34)*((ODM!L23-ODM!N16+1)-ODM!Q25)/(ODM!L23-ODM!N16+1),0) -> 0
B27: Pays principal de mission | D27: PAYS-BAS | P27: (établir demande de congés) | W27: Structure | X27: P/Act | Y27: Géo
B29: Structure : | D29: A10821-AGAP - PhenoMEn | H29: Projet/activité : | J29: C19966L01 | O29: Géo : | P29: =IFERROR(INDEX('Liste Géo'!A2:D260,MATCH(INDEX(Pays!A2:O250,MATCH(D27,Pays!A2:A250,0),15),'Liste Géo'!A2:A260,0),3),"") -> NL-Pays-Bas | W29: =IF(ISNA(INDEX('Liste Structure'!C2:D129,MATCH(ODM!D29,'Liste Structure'!C2:C129,0),2)),"",INDEX('Liste Structure'!C2:D129,MATCH(ODM!D29,'Liste Structure'!C2:C129,0),2)) -> A10821 | X29: =J29 -> C19966L01 | Y29: =IF(ISNA(INDEX('Liste Géo'!C2:D260,MATCH(ODM!P29,Géo,0),2)),"",INDEX('Liste Géo'!C2:D260,MATCH(ODM!P29,Géo,0),2)) -> NL
B31: Si mission à l'étranger, prendre connaissance de : | H31: Protocole de sécurisation | L31: Informations pratiques concernant la sécurité à l'étranger
B32: Pour information : | H32: Interlocuteurs G2M
B34: Informations financières | E34: Si la mission est tout ou partie facturable, préciser à qui :
E35: Si vous percevez des vacations ou honoraires, préciser le montant (€):
E36: Si vous percevez des perdiem, préciser le montant (€) :
F37: Commentaires :
B39: Budget prévisionnel | Q39: Montant (€)
B40: 1 - Frais engagés par l'agent soumis à autorisation préalable
B41: Indemnités Kilométriques (en cas d'utilisation du véhicule personnel) | O41: Nbr. Kilomètres : | Q41: =IFERROR(P41*VLOOKUP(D16,Pays!A1:L260,9,FALSE)/100,"") -> 0
B42: Forfait terrain (missions à l'étranger seulement) | O42: Nbr. de jours : | Q42: =P42*'autres ldv'!B26 -> 0
B43: (*) Une assurance obligatoire à charge du salarié doit être souscrite pour "déplacements professionnels"
B44: 2 - Frais à engager par l'agent (Hébergement, restauration, transport, autres…)
B45: Intercité + bus entre Amsterdam et Wageningen | Q45: 50
B46: Hébergement à Wageningen | Q46: 200
B47: Restauration à Wageningen | Q47: 150
B49: 3 - Frais engagés par le CIRAD (Achats par bons de commande)
B53: 4 - Indemnité de Sujétion prévisionnelle calculée | M53: IS hors charges | O53: Charges IS | Q53: IS charges comprises
M54: =IF(ISNA(Y23),"0",Y23) -> 0 | O54: =IF(ISNA(Y23),"0",Q54-Y23) -> 0 | Q54: =IF(ISNA(Y25),0,Y25) -> 0
K55: Total des frais budgétés (€) | Q55: =IFERROR(Q41+Q42+Q45+Q46+Q47+Q48+Q50+Q51+Q52+Q54,"") -> 400
B56: Total des frais engagés par le missionnaire (€) | Q56: =IFERROR(Q41+Q42+Q45+Q46+Q47+Q48,"") -> 400
B57: Montant de l'avance souhaitée (€)
B59: Commentaires :
F63: ORDRE DE MISSION
D67: Dpt. | F67: UR / Service | N67: Année | P67: N°Ordre
D68: =IF(D5="","",D5) -> Bios | F68: =IF(F5="","",F5) -> A10821-AGAP - PhenoMEn | N68: =IF(N5="","",N5) -> 2024 | P68: =IF(P5="","",P5) -> 111
C70: Nom : | G70: =IF(D9="","",D9) -> BRAUD | L70: Matricule : | O70: =IF(D7="","",D7) -> 30392
D71: Prénom : | G71: =IF(M9="","",M9) -> Oriane | L71: Structure : | O71: =IF(D29="","",D29) -> A10821-AGAP - PhenoMEn
C72: Pays d'affectation : | G72: =IF(F11="","",F11) -> FRANCE MÉTROPOLITAINE | L72: Projet/activité : | O72: =IF(J29="","",J29) -> C19966L01
C73: Pays de rattachement : | G73: =IF(P11="","",P11) -> FRANCE MÉTROPOLITAINE | L73: Géographie : | O73: =IF(P29="","",P29) -> NL-Pays-Bas
C75: Objet : | D75: =IF($D13="","",$D13) -> Rencontre de collaborateurs dans le projet IntercropValuES
E79: Date de la mission : | F79: du | G79: =IF(ISBLANK(N16),"",N16) -> 45345 | I79: au | J79: =IF(ISBLANK(L23),"",L23) -> 45351
K81: =IF(D17="","",D17&" - "&H17 ) -> FRANCE MÉTROPOLITAINE - Paris
K82: =IF(D18="","",D18&" - "&H18 ) -> PAYS-BAS - Wageningen
K83: =IF(D19="","",D19&" - "&H19 )
K84: =IF(D20="","",D20&" - "&H20 )
K85: =IF(D21="","",D21&" - "&H21 )
K86: =IF(D22="","",D22&" - "&H22 )
F88: Congés pris pendant la mission : | G88: du | H88: =IF(ISBLANK(D25),"",D25) -> 45346 | J88: au | K88: =IF(ISBLANK(G25),"",G25) -> 45347 | M88: et du | N88: =IF(ISBLANK(J25),"",J25) | P88: au | Q88: =IF(ISBLANK(M25),"",M25)
D91: Signatures | H91: Missionnaire | N91: Responsable
H92: Nom : | I92: =G70&" "&G71 -> BRAUD Oriane | N92: Nom : | O92: Pradal
H93: Date : | I93: 45335 | N93: Date : | O93: 45336
H94: Visa : | N94: Visa :
D96: Mention CNIL
D98: Consignes générales de sécurité : | H98: • La plus grande vigilance doit être prise en cas de retrait d'argent ou de change et lors des déplacements en ville. • En cas d'agression, il est recommandé de n'opposer aucune résistance. • En cas d'usage du véhicule personnel, une assurance obligatoire pour déplacements professionnels doit être souscrite par le missionnaire et à sa charge.
D102: En cas de mission à l'étranger, vous devez prendre connaissance :
H103: Protocole de Sécurisation
H104: http://intranet-dsst.cirad.fr/missions-et-mobilite/conseils
H105: N° d'urgence en toutes circonstances :
H106: ASSISTANCE International SOS N° contrat : 15AGDA924869 - Tél : +33 01 55 63 31 55
D109: Conseils voyages : | H109: • N° de l'équipe de conseillers Havas voyages : +33 04.99.51.58.14 - pluton@havasvoyages.fr • Horaires d'ouverture : du lundi au vendredi de 9h00 à 18h00 sans interruption. • N° du service d'urgence H24 en cas d'incident en dehors des heures d'ouverture de l'agence de voyage : Tel : +33 09.78.97.90.41 - (non surtaxé pour lappelant) et la prestation d'assistance est facturée au Cirad 35 euros par appel.
B113: www.cirad.fr
D114: Siège Social : 42 rue Scheffer, 75116 Paris, France Tél : +33 (0)1 53 70 20 00 SIRET 331 596 270 0040

Sheet NDF
G2: NOTE DE FRAIS DE MISSION | T2: =ODM!Q2 -> Formulaire DCAF
G3: =IF(ODM!D5="","",ODM!D5) -> Bios | I3: =IF(ODM!F5="","",ODM!F5) -> A10821-AGAP - PhenoMEn | O3: =IF(ODM!N5="","",ODM!N5) -> 2024 | Q3: =IF(ODM!P5="","",ODM!P5) -> 111 | T3: =ODM!Q3 -> 24/01/2024 | AB3: =ODM!W5 -> A10821-24-111
F4: N° d'ODM : | G4: =IF(ODM!W5="","",ODM!W5) -> A10821-24-111
E5: Mission Longue Durée : | F5: =ODM!Q16 -> NON | K5: Si OUI Indiquer | L5: N° NdF : | Q5: et période de liquidation du : | T5: au : | Z5: Type contrat | AB5: =ODM!W7 -> ALLR
E6: Nom, Prénom : | F6: =ODM!D9&" "&ODM!M9 -> BRAUD Oriane | L6: Matricule : | M6: =IF(ODM!D7="","",ODM!D7) -> 30392 | P6: Contrat : | Q6: =IF(ISBLANK(ODM!J7),"",ODM!J7) -> Doctorant Cirad | Z6: Structure | AB6: =IF(ISNA(INDEX('Liste Structure'!C2:D129,MATCH(D26,'Liste Structure'!C2:C129,0),2)),"",INDEX('Liste Structure'!C2:D129,MATCH(D26,'Liste Structure'!C2:C129,0),2)) -> A10821
E7: Pays d'affectation : | F7: =IF(ODM!F11="","",ODM!F11) -> FRANCE MÉTROPOLITAINE | P7: Pays ratt : | Q7: =IF(ODM!P11="","",ODM!P11) -> FRANCE MÉTROPOLITAINE | Z7: Act/projet | AB7: =K26 -> C19966L01
B8: Objet : | D8: =IF(ODM!D13="","",ODM!D13) -> Rencontre de collaborateurs dans le projet IntercropValuES | Z8: Géo | AB8: =IF(ISNA(INDEX('Liste Géo'!C2:D260,MATCH(R26,Géo,0),2)),"",INDEX('Liste Géo'!C2:D260,MATCH(R26,Géo,0),2)) -> NL
Q11: Infos pour GP
B12: Etape | D12: Pays visités | I12: Lieux | K12: Date arrivée jj/mm/aa | M12: Heure arrivée hh:mm | N12: Date de départ jj/mm/aa | P12: Heure départ hh:mm | Q12: congés reçu GP | R12: NdJ Missions | S12: Coef. Pays | T12: Jour IS et/ou bonif | U12: Montant IS hors charges | AB12: Arrivee | AC12: Depart | AD12: Durée jj | AE12: Durée hh | AF12: Durée j arrondie | AG12: H12 | AH12: N° d'étape | AI12: Etape avec jour à réaffecter | AK12: Pour pays principal :
B13: Début | D13: =IF(ODM!D16="","",ODM!D16) -> FRANCE MÉTROPOLITAINE | I13: =IF(ODM!H16="","",ODM!H16) -> Montpellier | N13: =IF(ODM!N16="","",ODM!N16) -> 45345 | P13: 0.70138889 | AC13: =IF(N13="","",N13+P13) -> 45345.701
B14: Pays 1 | D14: =IF(ODM!D17="","",ODM!D17) -> FRANCE MÉTROPOLITAINE | I14: =IF(ODM!H17="","",ODM!H17) -> Paris | K14: =IF(ODM!L17="","",ODM!L17) -> 45345 | M14: 0.84583333 | N14: =IF(ODM!N17="","",ODM!N17) -> 45348 | P14: 0.59861111 | Q14: =IF(K14="",0,IF(AND($E$22="",$H$22="",$K$22="",$N$22=""),0,IF(AND($E$22>=$N$13,$E$22<$N$14),IF($H$22<=$N$14,'autres ldv'!$D$2,'autres ldv'!$D$2-$H$22+$N$14))+IF(AND($E$22=$H$22,$E$22=$N$14),1)+IF(AND($K$22>=$N$13,$K$22<$N$14),IF($N$22<=$N$14,'autres ldv'!$D$3,'autres ldv'!$D$3-$N$22+$N$14))+IF(AND($K$22=$N$22,$K$22=$N$14,$N$14<>""),1))) -> 2 | R14: =IF(AD14="","",IF(AI14="",AF14-Q14,AF14+AI14-Q14)) -> 1 | S14: =IF(D14="","",IF(OR($F$7="",$Q$7=""),"",IF($F$7<>$Q$7,0,IF($D14=$F$7,0,IF(VLOOKUP($AB$5,'autres ldv'!$I$48:$K$59,3,FALSE)="Non",0,VLOOKUP($D14,Pays!$A$1:$M$261,VLOOKUP($Q$7,Pays!$A$1:$N$6,14,FALSE),FALSE)))))) -> 0 | T14: =IF(OR(D14=$F$7,AND($F$7<>$Q$7,D14="France métropolitaine")),0,R14) -> 0 | U14: =IF(S14="","",IF($AB$5="ALLR",IF($F$7="France métropolitaine",'autres ldv'!$B$45*S14*T14/30,'autres ldv'!$B$46*S14*T14/30),S14*T14*'autres ldv'!$B$43*'autres ldv'!$B$44/30)) -> 0 | Y14: =IF(ISNA(INDEX(Pays!A$2:O$260,MATCH(D14,Pays!A$2:A$260,0),15)),"",INDEX(Pays!A$2:O$260,MATCH(D14,Pays!A$2:A$260,0),15)) -> FR | AB14: =IF(K14="","",K14+M14) -> 45345.846 | AC14: =IF(N14="","",N14+P14) -> 45348.599 | AD14: =IF(K14="","",IF(N14="","",IF(K15="",INT(AB$20-AC13),INT(AC14-AC13)))) -> 2 | AE14: =IF(K14="","",IF(N14="","",IF(K15="",MOD(AB$20-AC13,1)*24,MOD(AC14-AC13,1)*24))) -> 21.533333 | AF14: =IF(AD14="","",IF(AE14>=12,AD14+1,AD14)) -> 3 | AG14: =IF($AE14="","",IF($AF$21=0,"",IF($AF$21>0,IF(AE14<12,AE14,""),IF(AE14>=12,AE14,"")))) | AH14: =IF(AG14="","",IF(AG14=$AG$21,ROW(AH14)-15,"")) | AI14: =IF(AH14="","",IF(AH14=$AH$21,$AF$21,"")) | AK14: =R14 -> 1 | AL14: =D14 -> FRANCE MÉTROPOLITAINE
B15: Pays 2 | D15: =IF(ODM!D18="","",ODM!D18) -> PAYS-BAS | I15: =IF(ODM!H18="","",ODM!H18) -> Wageningen | K15: =IF(ODM!L18="","",ODM!L18) -> 45348 | M15: 0.80486111 | N15: =IF(ODM!N18="","",ODM!N18) -> 45351 | P15: 0.625 | Q15: =IF(K15="",0,IF(AND($E$22="",$H$22="",$K$22="",$N$22=""),0,IF(AND($E$22>=$K15,$E$22<$N15),IF($H$22<=$N15,'autres ldv'!$D$2,'autres ldv'!$D$2-$H$22+$N15))+IF(AND($K$22>=$K15,$K$22<$N15),IF($N$22<=$N15,'autres ldv'!$D$3,'autres ldv'!$D$3-$N$22+$N15))+IF(AND($E$22>=$K14,$E$22<$N14,$H$22>N14),'autres ldv'!$D$2-NDF!Q14,0)+IF(AND($K$22>=$K14,$K$22<$N14,$N$22>N14),'autres ldv'!$D$3-NDF!Q14,0)+IF(AND($E$22=$H$22,$E$22=$N15,$N15<>""),1,0)+IF(AND($K$22=$N$22,$N$22=$N15,$N15<>""),1,0))) -> 0 | R15: =IF(AD15="","",IF(AI15="",AF15-Q15,AF15+AI15-Q15)) -> 3 | S15: =IF(D15="","",IF(OR($F$7="",$Q$7=""),"",IF($F$7<>$Q$7,0,IF($D15=$F$7,0,IF(VLOOKUP($AB$5,'autres ldv'!$I$48:$K$59,3,FALSE)="Non",0,VLOOKUP($D15,Pays!$A$1:$M$261,VLOOKUP($Q$7,Pays!$A$1:$N$6,14,FALSE),FALSE)))))) -> 0 | T15: =IF(OR(D15=$F$7,AND($F$7<>$Q$7,D15="France métropolitaine")),0,R15) -> 3 | U15: =IF(S15="","",IF($AB$5="ALLR",IF($F$7="France métropolitaine",'autres ldv'!$B$45*S15*T15/30,'autres ldv'!$B$46*S15*T15/30),S15*T15*'autres ldv'!$B$43*'autres ldv'!$B$44/30)) -> 0 | Y15: =IF(ISNA(INDEX(Pays!A$2:O$260,MATCH(D15,Pays!A$2:A$260,0),15)),"",INDEX(Pays!A$2:O$260,MATCH(D15,Pays!A$2:A$260,0),15)) -> NL | AB15: =IF(K15="","",K15+M15) -> 45348.805 | AC15: =IF(N15="","",N15+P15) -> 45351.625 | AD15: =IF(K15="","",IF(N15="","",IF(K16="",INT(AB$20-AC14),INT(AC15-AC14)))) -> 3 | AE15: =IF(K15="","",IF(N15="","",IF(K16="",MOD(AB$20-AC14,1)*24,MOD(AC15-AC14,1)*24))) -> 6.35 | AF15: =IF(AD15="","",IF(AE15>=12,AD15+1,AD15)) -> 3 | AG15: =IF($AE15="","",IF($AF$21=0,"",IF($AF$21>0,IF(AE15<12,AE15,""),IF(AE15>=12,AE15,"")))) | AH15: =IF(AG15="","",IF(AG15=$AG$21,ROW(AH15)-15,"")) | AI15: =IF(AH15="","",IF(AH15=$AH$21,$AF$21,"")) | AK15: =R15 -> 3 | AL15: =D15 -> PAYS-BAS
B16: Pays 3 | D16: =IF(ODM!D19="","",ODM!D19) | I16: =IF(ODM!H19="","",ODM!H19) | K16: =IF(ODM!L19="","",ODM!L19) | N16: =IF(ODM!N19="","",ODM!N19) | Q16: =IF(K16="",0,IF(AND($E$22="",$H$22="",$K$22="",$N$22=""),0,IF(AND($E$22>=$K16,$E$22<$N16),IF($H$22<=$N16,'autres ldv'!$D$2,'autres ldv'!$D$2-$H$22+$N16))+IF(AND($K$22>=$K16,$K$22<$N16),IF($N$22<=$N16,'autres ldv'!$D$3,'autres ldv'!$D$3-$N$22+$N16))+IF(AND($E$22>=$K15,$E$22<$N15,$H$22>N15),'autres ldv'!$D$2-NDF!Q15,0)+IF(AND($K$22>=$K15,$K$22<$N15,$N$22>N15),'autres ldv'!$D$3-NDF!Q15,0)+IF(AND($E$22=$H$22,$E$22=$N16,$N16<>""),1,0)+IF(AND($K$22=$N$22,$N$22=$N16,$N16<>""),1,0))) -> 0 | R16: =IF(AD16="","",IF(AI16="",AF16-Q16,AF16+AI16-Q16)) | S16: =IF(D16="","",IF(OR($F$7="",$Q$7=""),"",IF($F$7<>$Q$7,0,IF($D16=$F$7,0,IF(VLOOKUP($AB$5,'autres ldv'!$I$48:$K$59,3,FALSE)="Non",0,VLOOKUP($D16,Pays!$A$1:$M$261,VLOOKUP($Q$7,Pays!$A$1:$N$6,14,FALSE),FALSE)))))) | T16: =IF(OR(D16=$F$7,AND($F$7<>$Q$7,D16="France métropolitaine")),0,R16) | U16: =IF(S16="","",IF($AB$5="ALLR",IF($F$7="France métropolitaine",'autres ldv'!$B$45*S16*T16/30,'autres ldv'!$B$46*S16*T16/30),S16*T16*'autres ldv'!$B$43*'autres ldv'!$B$44/30)) | Y16: =IF(ISNA(INDEX(Pays!A$2:O$260,MATCH(D16,Pays!A$2:A$260,0),15)),"",INDEX(Pays!A$2:O$260,MATCH(D16,Pays!A$2:A$260,0),15)) | AB16: =IF(K16="","",K16+M16) | AC16: =IF(N16="","",N16+P16) | AD16: =IF(K16="","",IF(N16="","",IF(K17="",INT(AB$20-AC15),INT(AC16-AC15)))) | AE16: =IF(K16="","",IF(N16="","",IF(K17="",MOD(AB$20-AC15,1)*24,MOD(AC16-AC15,1)*24))) | AF16: =IF(AD16="","",IF(AE16>=12,AD16+1,AD16)) | AG16: =IF($AE16="","",IF($AF$21=0,"",IF($AF$21>0,IF(AE16<12,AE16,""),IF(AE16>=12,AE16,"")))) | AH16: =IF(AG16="","",IF(AG16=$AG$21,ROW(AH16)-15,"")) | AI16: =IF(AH16="","",IF(AH16=$AH$21,$AF$21,"")) | AK16: =R16 | AL16: =D16
B17: Pays 4 | D17: =IF(ODM!D20="","",ODM!D20) | I17: =IF(ODM!H20="","",ODM!H20) | K17: =IF(ODM!L20="","",ODM!L20) | N17: =IF(ODM!N20="","",ODM!N20) | Q17: =IF(K17="",0,IF(AND($E$22="",$H$22="",$K$22="",$N$22=""),0,IF(AND($E$22>=$K17,$E$22<$N17),IF($H$22<=$N17,'autres ldv'!$D$2,'autres ldv'!$D$2-$H$22+$N17))+IF(AND($K$22>=$K17,$K$22<$N17),IF($N$22<=$N17,'autres ldv'!$D$3,'autres ldv'!$D$3-$N$22+$N17))+IF(AND($E$22>=$K16,$E$22<$N16,$H$22>N16),'autres ldv'!$D$2-NDF!Q16,0)+IF(AND($K$22>=$K16,$K$22<$N16,$N$22>N16),'autres ldv'!$D$3-NDF!Q16,0)+IF(AND($E$22=$H$22,$E$22=$N17,$N17<>""),1,0)+IF(AND($K$22=$N$22,$N$22=$N17,$N17<>""),1,0))) -> 0 | R17: =IF(AD17="","",IF(AI17="",AF17-Q17,AF17+AI17-Q17)) | S17: =IF(D17="","",IF(OR($F$7="",$Q$7=""),"",IF($F$7<>$Q$7,0,IF($D17=$F$7,0,IF(VLOOKUP($AB$5,'autres ldv'!$I$48:$K$59,3,FALSE)="Non",0,VLOOKUP($D17,Pays!$A$1:$M$261,VLOOKUP($Q$7,Pays!$A$1:$N$6,14,FALSE),FALSE)))))) | T17: =IF(OR(D17=$F$7,AND($F$7<>$Q$7,D17="France métropolitaine")),0,R17) | U17: =IF(S17="","",IF($AB$5="ALLR",IF($F$7="France métropolitaine",'autres ldv'!$B$45*S17*T17/30,'autres ldv'!$B$46*S17*T17/30),S17*T17*'autres ldv'!$B$43*'autres ldv'!$B$44/30)) | Y17: =IF(ISNA(INDEX(Pays!A$2:O$260,MATCH(D17,Pays!A$2:A$260,0),15)),"",INDEX(Pays!A$2:O$260,MATCH(D17,Pays!A$2:A$260,0),15)) | AB17: =IF(K17="","",K17+M17) | AC17: =IF(N17="","",N17+P17) | AD17: =IF(K17="","",IF(N17="","",IF(K18="",INT(AB$20-AC16),INT(AC17-AC16)))) | AE17: =IF(K17="","",IF(N17="","",IF(K18="",MOD(AB$20-AC16,1)*24,MOD(AC17-AC16,1)*24))) | AF17: =IF(AD17="","",IF(AE17>=12,AD17+1,AD17)) | AG17: =IF($AE17="","",IF($AF$21=0,"",IF($AF$21>0,IF(AE17<12,AE17,""),IF(AE17>=12,AE17,"")))) | AH17: =IF(AG17="","",IF(AG17=$AG$21,ROW(AH17)-15,"")) | AI17: =IF(AH17="","",IF(AH17=$AH$21,$AF$21,"")) | AK17: =R17 | AL17: =D17
B18: Pays 5 | D18: =IF(ODM!D21="","",ODM!D21) | I18: =IF(ODM!H21="","",ODM!H21) | K18: =IF(ODM!L21="","",ODM!L21) | N18: =IF(ODM!N21="","",ODM!N21) | Q18: =IF(K18="",0,IF(AND($E$22="",$H$22="",$K$22="",$N$22=""),0,IF(AND($E$22>=$K18,$E$22<$N18),IF($H$22<=$N18,'autres ldv'!$D$2,'autres ldv'!$D$2-$H$22+$N18))+IF(AND($K$22>=$K18,$K$22<$N18),IF($N$22<=$N18,'autres ldv'!$D$3,'autres ldv'!$D$3-$N$22+$N18))+IF(AND($E$22>=$K17,$E$22<$N17,$H$22>N17),'autres ldv'!$D$2-NDF!Q17,0)+IF(AND($K$22>=$K17,$K$22<$N17,$N$22>N17),'autres ldv'!$D$3-NDF!Q17,0)+IF(AND($E$22=$H$22,$E$22=$N18,$N18<>""),1,0)+IF(AND($K$22=$N$22,$N$22=$N18,$N18<>""),1,0))) -> 0 | R18: =IF(AD18="","",IF(AI18="",AF18-Q18,AF18+AI18-Q18)) | S18: =IF(D18="","",IF(OR($F$7="",$Q$7=""),"",IF($F$7<>$Q$7,0,IF($D18=$F$7,0,IF(VLOOKUP($AB$5,'autres ldv'!$I$48:$K$59,3,FALSE)="Non",0,VLOOKUP($D18,Pays!$A$1:$M$261,VLOOKUP($Q$7,Pays!$A$1:$N$6,14,FALSE),FALSE)))))) | T18: =IF(OR(D18=$F$7,AND($F$7<>$Q$7,D18="France métropolitaine")),0,R18) | U18: =IF(S18="","",IF($AB$5="ALLR",IF($F$7="France métropolitaine",'autres ldv'!$B$45*S18*T18/30,'autres ldv'!$B$46*S18*T18/30),S18*T18*'autres ldv'!$B$43*'autres ldv'!$B$44/30)) | Y18: =IF(ISNA(INDEX(Pays!A$2:O$260,MATCH(D18,Pays!A$2:A$260,0),15)),"",INDEX(Pays!A$2:O$260,MATCH(D18,Pays!A$2:A$260,0),15)) | AB18: =IF(K18="","",K18+M18) | AC18: =IF(N18="","",N18+P18) | AD18: =IF(K18="","",IF(N18="","",IF(K19="",INT(AB$20-AC17),INT(AC18-AC17)))) | AE18: =IF(K18="","",IF(N18="","",IF(K19="",MOD(AB$20-AC17,1)*24,MOD(AC18-AC17,1)*24))) | AF18: =IF(AD18="","",IF(AE18>=12,AD18+1,AD18)) | AG18: =IF($AE18="","",IF($AF$21=0,"",IF($AF$21>0,IF(AE18<12,AE18,""),IF(AE18>=12,AE18,"")))) | AH18: =IF(AG18="","",IF(AG18=$AG$21,ROW(AH18)-15,"")) | AI18: =IF(AH18="","",IF(AH18=$AH$21,$AF$21,"")) | AK18: =R18 | AL18: =D18
B19: Pays 6 | D19: =IF(ODM!D22="","",ODM!D22) | I19: =IF(ODM!H22="","",ODM!H22) | K19: =IF(ODM!L22="","",ODM!L22) | N19: =IF(ODM!N22="","",ODM!N22) | Q19: =IF(K19="",0,IF(AND($E$22="",$H$22="",$K$22="",$N$22=""),0,IF(AND($E$22>=$K19,$E$22<$K$20),IF($H$22<=$K$20,'autres ldv'!$D$2,'autres ldv'!$D$2-$H$22+$K$20))+IF(AND($K$22>=$K19,$K$22<$K$20),IF($N$22<=$K$20,'autres ldv'!$D$3,'autres ldv'!$D$3-$N$22+$K$20))+IF(AND($E$22>=$K18,$E$22<$N18,$H$22>N18),'autres ldv'!$D$2-NDF!Q18,0)+IF(AND($K$22>=$K18,$K$22<$N18,$N$22>N18),'autres ldv'!$D$3-NDF!Q18,0)+IF(AND($E$22=$H$22,$E$22=$K$20,$E$22<>""),1)+IF(AND($K$22=$N$22,$K$22=$K$20,$K$22<>""),1))) -> 0 | R19: =IF(AD19="","",IF(AI19="",AF19-Q19,AF19+AI19-Q19)) | S19: =IF(D19="","",IF(OR($F$7="",$Q$7=""),"",IF($F$7<>$Q$7,0,IF($D19=$F$7,0,IF(VLOOKUP($AB$5,'autres ldv'!$I$48:$K$59,3,FALSE)="Non",0,VLOOKUP($D19,Pays!$A$1:$M$261,VLOOKUP($Q$7,Pays!$A$1:$N$6,14,FALSE),FALSE)))))) | T19: =IF(OR(D19=$F$7,AND($F$7<>$Q$7,D19="France métropolitaine")),0,R19) | U19: =IF(S19="","",IF($AB$5="ALLR",IF($F$7="France métropolitaine",'autres ldv'!$B$45*S19*T19/30,'autres ldv'!$B$46*S19*T19/30),S19*T19*'autres ldv'!$B$43*'autres ldv'!$B$44/30)) | Y19: =IF(ISNA(INDEX(Pays!A$2:O$260,MATCH(D19,Pays!A$2:A$260,0),15)),"",INDEX(Pays!A$2:O$260,MATCH(D19,Pays!A$2:A$260,0),15)) | AB19: =IF(K19="","",K19+M19) | AC19: =IF(N19="","",N19+P19) | AD19: =IF(K19="","",IF(N19="","",INT(AB$20-AC18))) | AE19: =IF(K19="","",IF(N19="","",IF(K20="",MOD(AB$20-AC18,1)*24,MOD(AC19-AC18,1)*24))) | AF19: =IF(AD19="","",IF(AE19>=12,AD19+1,AD19)) | AG19: =IF($AE19="","",IF($AF$21=0,"",IF($AF$21>0,IF(AE19<12,AE19,""),IF(AE19>=12,AE19,"")))) | AH19: =IF(AG19="","",IF(AG19=$AG$21,ROW(AH19)-15,"")) | AI19: =IF(AH19="","",IF(AH19=$AH$21,$AF$21,"")) | AK19: =R19 | AL19: =D19
B20: Fin | D20: =IF(ODM!D23="","",ODM!D23) -> FRANCE MÉTROPOLITAINE | I20: =IF(ODM!H23="","",ODM!H23) -> Paris | K20: =IF(ODM!L23="","",ODM!L23) -> 45351 | M20: 0.86319444 | Q20: =SUM(Q14:Q19) -> 2 | R20: =SUM(R14:R19) -> 4 | U20: =SUM(U14:V19) -> 0 | AB20: =IF(K20="","",K20+M20) -> 45351.863 | AD20: =IF(K20="","",INT(AB$20-AC$13)) -> 6 | AE20: =MOD(AB20-AC13,1)*24 -> 3.8833333 | AF20: =IF(AD20="","",IF(AE20>=12,AD20+1,AD20)) -> 6
AE21: Ecart : | AF21: =AF20-SUM(AF14:AF19) -> 0 | AG21: =IF($AF$21="","",IF($AF$21=0,"",IF($AF$21>0,MAX(AG14:AG19),MIN(AG14:AG19)))) | AH21: =IF($AF$21="","",IF($AF$21=0,"",MIN(AH14:AH19)))
D22: *Congés du | E22: =IF(ODM!D25="","",ODM!D25) -> 45346 | G22: au | H22: =IF(ODM!G25="","",ODM!G25) -> 45347 | J22: et du | K22: =IF(ODM!J25="","",ODM!J25) | M22: au | N22: =IF(ODM!M25="","",ODM!M25) | P22: =IF(Q22=0,"",'autres ldv'!D2&"+"&'autres ldv'!D3) -> 2+0 | Q22: =IFERROR('autres ldv'!D2+'autres ldv'!D3,0) -> 2 | R22: =IF(N13="",0,IF(N13=K20,1,(((K20+M20)-(N13+P13))-Q20))) -> 4.1618056 | S22: Pour vérif du report des congés | AG22: VREFH12 | AH22: MINETAPE
B24: Pays principal | E24: =IFERROR(VLOOKUP(MAX(AK14:AK19),AK14:AL19,2,FALSE),"") -> PAYS-BAS
C26: Structure | D26: =IF(ODM!D29="","",ODM!D29) -> A10821-AGAP - PhenoMEn | J26: Projet/Act | K26: =IF(ODM!J29="","",ODM!J29) -> C19966L01 | Q26: Géo | R26: =IFERROR(INDEX('Liste Géo'!A2:D260,MATCH(INDEX(Pays!A2:O250,MATCH(E24,Pays!A2:A250,0),15),'Liste Géo'!A2:A260,0),3),"") -> NL-Pays-Bas
B28: Hébergement & Restauration | T28: Total : | U28: =SUM(T30:V34,U38:V71,U75:V76) -> 135.58
B29: Hébergement / Restauration France Métropolitaine | O29: N° justif. | P29: Montant € | R29: Quantité | T29: Montant €
B30: Hébergement sur justificatifs (soumis à plafond) | I30: Ile de France (75,77,78,91,92,93,94,95) | T30: =(IF($R30="","",ROUND(IF(($P30/$R30)>'autres ldv'!B28,$R30*'autres ldv'!B28,$P30),2)))
I31: Province | T31: =(IF($R31="","",ROUND(IF(($P31/$R31)>'autres ldv'!B29,$R31*'autres ldv'!B29,$P31),2)))
B32: Hébergement sans justificatif (forfait) | I32: Région Parisienne (75,92,93,94) | T32: =IF($R32="","",ROUND($R32*'autres ldv'!B30,2))
I33: Province | T33: =IF($R33="","",ROUND($R33*'autres ldv'!B31,2))
B34: Restauration (forfait) | I34: France métropolitaine | T34: =IF($R34="","",ROUND($R34*'autres ldv'!B32,2))
B37: Libellé hébergement / Restauration hors France métropolitaine | L37: N° justif. | M37: date | O37: Devise | Q37: Mt. en devise | S37: Taux (1€ = )* | U37: Montant €
B38: Restauration lundi 26/02 midi | L38: 1 | M38: 45348 | Q38: 10.7 | S38: 1 | U38: =IF($Q38="","",ROUND($Q38/$S38,2)) -> 10.7
B39: Restauration lundi 26/02 soir | L39: 2 | M39: 45348 | Q39: 24.5 | S39: 1 | U39: =IF($Q39="","",ROUND($Q39/$S39,2)) -> 24.5
B40: Restauration mardi 27/02 midi | L40: 3 | M40: 45349 | Q40: 22.34 | S40: 1 | U40: =IF($Q40="","",ROUND($Q40/$S40,2)) -> 22.34
B41: Restauration mardi 27/02 soir | L41: 2 | M41: 45349 | Q41: 13.5 | S41: 1 | U41: =IF($Q41="","",ROUND($Q41/$S41,2)) -> 13.5
B42: Restauration mercredi 28/02 midi | L42: 4 | M42: 45350 | Q42: 14.18 | S42: 1 | U42: =IF($Q42="","",ROUND($Q42/$S42,2)) -> 14.18
B43: Restauration mercredi 28/02 soir | L43: 5 | M43: 45350 | Q43: 16.5 | S43: 1 | U43: =IF($Q43="","",ROUND($Q43/$S43,2)) -> 16.5
B44: Restauration jeudi 29/02 midi | L44: 6 | M44: 45351 | Q44: 16.63 | S44: 1 | U44: =IF($Q44="","",ROUND($Q44/$S44,2)) -> 16.63
B45: Restauration jeudi 29/02 soir | L45: 7 | M45: 45351 | Q45: 8.23 | S45: 1 | U45: =IF($Q45="","",ROUND($Q45/$S45,2)) -> 8.23
B46: Taxe de séjour | L46: 8 | M46: 45348 | Q46: 9 | S46: 1 | U46: =IF($Q46="","",ROUND($Q46/$S46,2)) -> 9
U47: =IF($Q47="","",ROUND($Q47/$S47,2))
U48: =IF($Q48="","",ROUND($Q48/$S48,2))
U49: =IF($Q49="","",ROUND($Q49/$S49,2))
U50: =IF($Q50="","",ROUND($Q50/$S50,2))
U51: =IF($Q51="","",ROUND($Q51/$S51,2))
U52: =IF($Q52="","",ROUND($Q52/$S52,2))
U53: =IF($Q53="","",ROUND($Q53/$S53,2))
U54: =IF($Q54="","",ROUND($Q54/$S54,2))
U55: =IF($Q55="","",ROUND($Q55/$S55,2))
U56: =IF($Q56="","",ROUND($Q56/$S56,2))
U57: =IF($Q57="","",ROUND($Q57/$S57,2))
U58: =IF($Q58="","",ROUND($Q58/$S58,2))
... U71: =IF($Q71="","",ROUND($Q71/$S71,2))
B74: Forfait terrain (étranger) Décrire ci-dessous la situation : | S74: Quantité | U74: Montant €
Q75: repas | U75: =IF($S75="","",ROUND($S75*'autres ldv'!B24,2))
Q76: nuitées | U76: =IF($S76="","",ROUND($S76*'autres ldv'!B25,2))
B80: Transport | T80: Total : | U80: =SUM(U82:V83,U86:V108) -> 42.8
B81: Indemnité kilométrique | H81: Véhicule | J81: N° justif | K81: Pays | S81: Nbrs. Kms | U81: Montant €
B82: véhicule personnel sur route | U82: =IF(S82="","",IF(H82="","",ROUND(IF(K82="","",VLOOKUP(H82,'autres ldv'!A$19:B$21,2,FALSE)*S82*VLOOKUP(K82,Pays!A$1:K$261,9,FALSE)/100),2)))
B83: véhicule personnel sur piste | U83: =IF(S83="","",IF(H83="","",ROUND(IF(K83="","",VLOOKUP(H83,'autres ldv'!A$19:B$21,2,FALSE)*S83*VLOOKUP(K83,Pays!A$1:K$261,10,FALSE)/100),2)))
B85: Transport (frais réels) | L85: N° justif. | M85: date | O85: Devise | Q85: Mt. en devise | S85: Taux (1€ = )* | U85: Montant €
B86: Intercity Amsterdam Centraal -- Ede-Wageningen station | L86: 9 | M86: 45348 | Q86: 17.9 | S86: 1 | U86: =IF($Q86="","",ROUND($Q86/$S86,2)) -> 17.9
B87: Intercity Ede-Wageningen station -- Amsterdam Centraal | L87: 10 (billet électronique) | M87: 45351 | Q87: 16.9 | S87: 1 | U87: =IF($Q87="","",ROUND($Q87/$S87,2)) -> 16.9
B88: Bus Ede-Wageningen station -- Wageningen | L88: 11 (relevé de compte) | M88: 45348 | Q88: 4 | S88: 1 | U88: =IF($Q88="","",ROUND($Q88/$S88,2)) -> 4
B89: Bus Wageningen -- Ede-Wageningen station | L89: 11 (relevé de compte) | M89: 45351 | Q89: 4 | S89: 1 | U89: =IF($Q89="","",ROUND($Q89/$S89,2)) -> 4
U90: =IF($Q90="","",ROUND($Q90/$S90,2))
U91: =IF($Q91="","",ROUND($Q91/$S91,2))
U92: =IF($Q92="","",ROUND($Q92/$S92,2))
U93: =IF($Q93="","",ROUND($Q93/$S93,2))
U94: =IF($Q94="","",ROUND($Q94/$S94,2))
U95: =IF($Q95="","",ROUND($Q95/$S95,2))
U96: =IF($Q96="","",ROUND($Q96/$S96,2))
U97: =IF($Q97="","",ROUND($Q97/$S97,2))
U98: =IF($Q98="","",ROUND($Q98/$S98,2))
U99: =IF($Q99="","",ROUND($Q99/$S99,2))
U100: =IF($Q100="","",ROUND($Q100/$S100,2))
U101: =IF($Q101="","",ROUND($Q101/$S101,2))
... U108: =IF($Q108="","",ROUND($Q108/$S108,2))
B112: Autres frais | T112: Total : | U112: =SUM(U114:V141) -> 0
B113: Libellé | I113: N° Justif. | J113: Date | L113: Devise | M113: Montant HT | O113: TVA | Q113: Montant TTC | S113: Taux (1€ = )* | U113: Montant €
U114: =IF($Q114="","",ROUND($Q114/$S114,2))
U115: =IF($Q115="","",ROUND($Q115/$S115,2))
U116: =IF($Q116="","",ROUND($Q116/$S116,2))
U117: =IF($Q117="","",ROUND($Q117/$S117,2))
U118: =IF($Q118="","",ROUND($Q118/$S118,2))
U119: =IF($Q119="","",ROUND($Q119/$S119,2))
U120: =IF($Q120="","",ROUND($Q120/$S120,2))
U121: =IF($Q121="","",ROUND($Q121/$S121,2))
U122: =IF($Q122="","",ROUND($Q122/$S122,2))
U123: =IF($Q123="","",ROUND($Q123/$S123,2))
U124: =IF($Q124="","",ROUND($Q124/$S124,2))
U125: =IF($Q125="","",ROUND($Q125/$S125,2))
... U141: =IF($Q141="","",ROUND($Q141/$S141,2))
S144: Total général des frais : | T144: =IF(F6="",0,U112+U80+U28) -> 178.38
S145: Avance à déduire : | T145: =ODM!Q57 -> 0
B148: Autres montants perçus
B149: Libellé | L149: N° justif. | M149: date | O149: Devise | Q149: Mt. en devise | S149: Taux (1€ = )* | U149: Montant €
B150: Honoraires | U150: =IF($S150=0,0,ROUND($Q150/$S150,2)) -> 0
B151: Perdiem | U151: =IF($S151=0,0,ROUND($Q151/$S151,2)) -> 0
B154: (*) | C154: Taux de Change | S154: Total montants perçus : | T154: =SUM(U150:V151) -> 0
S155: Net à rembourser : | T155: =T144-(ROUND(T145,2)+T154) -> 178.38
N156: =IF(T155<0,"pour le remboursement, vous reporter à la procédure de l'onglet Aide à la saisie","")
...

Sheet Mention CNIL
B3: DCAF-G2M
B8: "Les informations recueillies font l'objet d'un traitement informatique destiné à suivre les missions du CIRAD. Les destinataires des données sont les gestionnaires des missions et de la mobilité géographique (G2M). Conformément à la loi " informatique et libertés " du 6 janvier 1978, vous bénéficiez d'un droit d'accès et de rectification aux informations qui vous concernent. Si vous souhaitez exercer ce droit et obtenir communication des informations vous concernant, veuillez-vous adresser au service DCAF-G2M. Vous pouvez également, pour des motifs légitimes, vous opposer au traitement des données vous concernant."
A24: www.cirad.fr
B26: Siège Social : 42 rue Scheffer, 75116 Paris, France Tél : +33 (0)1 53 70 20 00 SIRET 331 596 270 0040

Sheet AgoraODM
A1: oesae.en3oesae | B1: oesae.v05oesae | C1: oesae.v09oesae | D1: oesae.v06oesae | E1: oesae.dt2oesae | F1: oesae.v09oesae | G1: oesae.v10oesae | H1: oesae.dt1oesae | I1: oesae.dt5oesae | J1: oesae.lb1oesae | K1: oesae.nu2oesae | L1: oesae.nu3oesae | M1: oesae.n19oesae | N1: oesae.v02oesae | O1: oesae.v03oesae | P1: oesae.v04oesae | Q1: oesae.v07oesae | R1: oesae.etsoesae | S1: oesae.evtoesae | T1: oesae.n11oesae | U1: oesae.n12oesae | V1: oesae.e10oesae
A2: N° d'ordre de mission | B2: Pays principal mission | C2: Pays de rattachement | D2: N° matricule | E2: Date de réception ODM | F2: Pays de rattachement | G2: Pays d'affectation | H2: au | I2: au | J2: Commentaire | K2: Total des frais budgété | L2: Montant budgété des frais engagés par l'agent | M2: Montant de l'avance | N2: Structure | O2: Projet/Activité | P2: Géographie | Q2: CGR Complet | R2: Etablissement | S2: Code évènement | T2: Charges IS | U2: IS hors charges | V2: Type de personne
A3: =ODM!W5 -> A10821-24-111 | B3: =VLOOKUP(ODM!D27,Pays!$A$2:$O$254,15,FALSE) -> NL | C3: =VLOOKUP(ODM!P11,Pays!$A$2:$O$252,15,FALSE) -> FR | D3: ="P"&ODM!D7 -> P30392 | E3: =IF(ISBLANK(ODM!O93),TODAY(),ODM!O93) -> 45336 | F3: =VLOOKUP(ODM!P11,Pays!$A$2:$O$252,15,FALSE) -> FR | G3: =VLOOKUP(ODM!F11,Pays!$A$2:$O$252,15,FALSE) -> FR | H3: =ODM!N16 -> 45345 | I3: =ODM!L23 -> 45351 | K3: =ODM!Q55 -> 400 | L3: =IF(ODM!Q56=0,"",ODM!Q56) -> 400 | M3: =IF(ODM!Q57=0,"",ODM!Q57) | N3: =ODM!W29 -> A10821 | O3: =ODM!X29 -> C19966L01 | P3: =ODM!Y29 -> NL | Q3: =N3&REPT(" ",(7-LEN(N3)))&O3&REPT(" ",(10-LEN(O3)))&P3 -> A10821 C19966L01 NL | R3: CIRAD | S3: YSODM | T3: =IF(ODM!O54=0,"",ROUND(ODM!O54,0)) | U3: =IF(ODM!M54=0,"",ROUND(ODM!M54,0)) | V3: =IFERROR(VLOOKUP(ODM!J7,'autres ldv'!J48:N55,5,0),"") -> 200

Sheet AgoraNDF
A1: oesae.en3oesae | B1: oesae.v05oesae | C1: oesae.v06oesae | D1: oesae.dt2oesae | E1: oesae.v09oesae | F1: oesae.v10oesae | G1: oesae.dt1oesae | H1: oesae.dt5oesae | I1: oesae.dt3oesae | J1: oesae.dt4oesae | K1: oesae.lb1oesae | L1: oesae.n17oesae | M1: oesae.nu2oesae | N1: oesae.nu4oesae | O1: oesae.nu3oesae | P1: oesae.nu5oesae | Q1: oesae.n19oesae | R1: oesae.v02oesae | S1: oesae.v03oesae | T1: oesae.v04oesae | U1: oesae.v07oesae | V1: oesae.id1oesae | W1: oesae.id5oesae | X1: oesae.en4oesae | Y1: oesae.n11oesae | Z1: oesae.id2oesae | AA1: oesae.id6oesae | AB1: oesae.en5oesae | AC1: oesae.n12oesae | AD1: oesae.id3oesae | AE1: oesae.id7oesae | AF1: oesae.en6oesae | AG1: oesae.n13oesae | AH1: oesae.id4oesae | AI1: oesae.id8oesae | AJ1: oesae.en7oesae | AK1: oesae.n14oesae | AL1: oesae.i10oesae | AM1: oesae.i12oesae | AN1: oesae.en8oesae | AO1: oesae.n15oesae | AP1: oesae.i11oesae | AQ1: oesae.i14oesae | AR1: oesae.i13oesae | AS1: oesae.n16oesae | AT1: oesae.lb2oesae | AU1: oesae.etsoesae | AV1: oesae.evtoesae | AW1: oesae.e10oesae
A2: N° d'ordre de mission | B2: Pays principal mission | C2: N° matricule | D2: Date de réception NDF | E2: Pays de rattachement | F2: Pays d'affectation | G2: Mission du | H2: au | I2: Congés du | J2: au | K2: Commentaire | L2: Montant des attestations sur l’honneur | M2: Hébergement/Restauration | N2: + Autres frais | O2: + Transport | P2: - Autres montants perçus | Q2: = Total note de frais | R2: Structure | S2: Projet/Activité | T2: Géographie | U2: CGR complet | V2: Pays 1 | W2: Nb jours pays 1 | X2: Coef pays 1 | Y2: Montant pays 1 | Z2: Pays 2 | AA2: Nb jours pays 2 | AB2: Coef pays 2 | AC2: Montant pays 2 | AD2: Pays 3 | AE2: Nb jours pays 3 | AF2: Coef pays 3 | AG2: Montant pays 3 | AH2: Pays 4 | AI2: Nb jours pays 4 | AJ2: Coef pays 4 | AK2: Montant pays 4 | AL2: Pays 5 | AM2: Nb jours pays 5 | AN2: Coef pays 5 | AO2: Montant pays 5 | AP2: Pays 6 | AQ2: Coef pays 6 | AR2: Nb jours pays 6 | AS2: Montant pays 6 | AT2: Ventilation DSN | AU2: Etablissement | AV2: Code évènement | AW2: Type de personne
A3: =ODM!W5 -> A10821-24-111 | B3: =VLOOKUP(NDF!E24,Pays!$A$2:$O$254,15,FALSE) -> NL | C3: ="P"&ODM!D7 -> P30392 | D3: =IF(ISBLANK(NDF!U159),TODAY(),NDF!U159) -> 45376 | E3: =VLOOKUP(ODM!P11,Pays!$A$2:$O$252,15,FALSE) -> FR | F3: =VLOOKUP(ODM!F11,Pays!$A$2:$O$252,15,FALSE) -> FR | G3: =NDF!N13 -> 45345 | H3: =NDF!K20 -> 45351 | I3: =NDF!E22 -> 45346 | J3: =NDF!H22 -> 45347 | K3: =IF(NDF!P162="","",NDF!P162) | L3: =ROUND(NDF!U160,2) -> 0 | M3: =IF(NDF!$U28=0,"",NDF!$U28) -> 135.58 | N3: =IF(NDF!$U112=0,"",NDF!$U112) | O3: =IF(NDF!$U80=0,"",NDF!$U80) -> 42.8 | P3: =IF(NDF!$T154=0,"",NDF!$T154) | Q3: =NDF!U28+NDF!U80+NDF!U112-NDF!T154 -> 178.38 | R3: =NDF!$AB6 -> A10821 | S3: =NDF!AB7 -> C19966L01 | T3: =NDF!$AB8 -> NL | U3: =R3&REPT(" ",(7-LEN(R3)))&S3&REPT(" ",(10-LEN(S3)))&T3 -> A10821 C19966L01 NL | V3: =NDF!$Y14 -> FR | W3: =NDF!$R14 -> 1 | X3: =NDF!$S14 -> 0 | Y3: =NDF!U14 -> 0 | Z3: =NDF!$Y15 -> NL | AA3: =NDF!$R15 -> 3 | AB3: =NDF!$S15 -> 0 | AC3: =NDF!$U15 -> 0 | AD3: =NDF!$Y16 | AE3: =NDF!$R16 | AF3: =NDF!$S16 | AG3: =NDF!$U16 | AH3: =NDF!$Y17 | AI3: =NDF!$R17 | AJ3: =NDF!$S17 | AK3: =NDF!$U17 | AL3: =NDF!$Y18 | AM3: =NDF!$R18 | AN3: =NDF!$S18 | AO3: =NDF!$U18 | AP3: =NDF!$Y19 | AQ3: =NDF!$S19 | AR3: =NDF!$R19 | AS3: =NDF!$U19 | AT3: =LEFT(ODM!J7,30) -> Doctorant Cirad | AU3: CIRAD | AV3: YSNDF | AW3: =IFERROR(VLOOKUP(NDF!Q6,'autres ldv'!J48:N55,5,0),"") -> 200

Sheet Pays
B1: Continent (selon table RH des coef.d'eloignement) Un blanc = pays non existant en table RH des coeff d'éloignement | C1: X = pays en table RH des coef.d'eloignement | D1: Coef d'IS (= Coef d'éloignement, sauf Europe=0 ) Ratt : France | E1: Coef d'IS (= Coef d'éloignement, sauf Europe=0 ) Ratt : Martinique | F1: Coef d'IS (= Coef d'éloignement, sauf Europe=0 ) Ratt : Guadeloupe | G1: Coef d'IS (= Coef d'éloignement, sauf Europe=0 ) Ratt : Guyane | H1: Coef d'IS (= Coef d'éloignement, sauf Europe=0 ) Ratt : Réunion | I1: IK Route - Montant pour 100 km | J1: IK Piste - Montant pour 100 km | K1: Pour calculateur Montant moyen de 2 restauration + 1 hébergement (€) | L1: Coef d'IS (= Coef d'éloignement, sauf Europe=0 ) Ratt : Mayotte | M1: Pour calcul IS | N1: Colonne Coef d'IS à appliquer pour recherchev | O1: Analytique Géo | R1: Sites de rattachement
A2: FRANCE MÉTROPOLITAINE | B2: Europe | C2: x | D2: 0 | E2: 0.25 | F2: 0.25 | G2: 0.3 | H2: 0.3 | I2: 52.9 | K2: 118 | L2: 0 | M2: France | N2: 4 | O2: FR | R2: FRANCE MÉTROPOLITAINE
A3: REUNION | B3: DOM | C3: x | D3: 0.3 | E3: 0.3 | F3: 0.3 | G3: 0.35 | H3: 0 | I3: 52.9 | K3: 140 | L3: NC | M3: Dom | N3: 8 | O3: RE | R3: REUNION
A4: GUADELOUPE | B4: DOM | C4: x | D4: 0.25 | E4: 0.2 | F4: 0 | G4: 0.25 | H4: 0.3 | I4: 52.9 | K4: 143 | L4: NC | M4: Dom | N4: 6 | O4: GP | R4: GUADELOUPE
A5: MARTINIQUE | B5: DOM | C5: x | D5: 0.25 | E5: 0 | F5: 0.2 | G5: 0.25 | H5: 0.3 | I5: 52.9 | K5: 143 | L5: NC | M5: Dom | N5: 5 | O5: MQ | R5: MARTINIQUE
A6: GUYANE FRANCAISE | B6: DOM | C6: x | D6: 0.3 | E6: 0.25 | F6: 0.25 | G6: 0 | H6: 0.35 | I6: 52.9 | K6: 150 | L6: NC | M6: Dom | N6: 7 | O6: GF | R6: GUYANE FRANCAISE
A7: MAYOTTE | B7: DOM | C7: x | D7: 0.33 | E7: NC | F7: 0.34 | G7: NC | H7: 0.3 | I7: 52.9 | K7: 161 | L7: NC | M7: Etranger | N7: 12 | O7: YT | R7: MAYOTTE
A8: AFGHANISTAN | C8: x | D8: NC | E8: NC | F8: NC | G8: NC | H8: NC | K8: 0 | L8: NC | M8: Etranger | O8: AF
A9: AFRIQUE DU SUD | B9: Afrique non Francophone | C9: x | D9: 0.39 | E9: NC | F9: 0.42 | G9: NC | H9: 0.4 | I9: 38.2 | K9: 64 | L9: NC | M9: Etranger | O9: ZA
A10: ALBANIE | B10: Europe | D10: 0 | E10: 0 | F10: 0 | G10: 0 | H10: 0 | K10: 100 | L10: 0 | M10: Etranger | O10: AL
A11: ALGERIE | B11: Afriq. Nord, P&M-Orient | C11: x | D11: 0.43 | E11: NC | F11: NC | G11: NC | H11: NC | K11: 75 | L11: NC | M11: Etranger | O11: DZ
A12: ALLEMAGNE | B12: Europe | C12: x | D12: 0 | E12: 0 | F12: 0 | G12: 0 | H12: 0 | K12: 100 | L12: 0 | M12: Etranger | O12: DE
A13: ANDORRE | B13: Europe | C13: x | D13: 0 | E13: 0 | F13: 0 | G13: 0 | H13: 0 | K13: 100 | L13: 0 | M13: Etranger | O13: AD
A14: ANGOLA | B14: Afrique non Francophone | C14: x | D14: NC | E14: NC | F14: NC | G14: NC | H14: NC | K14: 75 | L14: 0 | M14: Etranger | O14: AO
A15: ANGUILLA | D15: NC | E15: NC | F15: NC | G15: NC | H15: NC | K15: 0 | L15: 0 | M15: Etranger | O15: AI
A16: ANTARCTIQUE | D16: NC | E16: NC | F16: NC | G16: NC | H16: NC | K16: 0 | L16: 0 | M16: Etranger | O16: AQ
A17: ANTIGUA ET BARBUDA | B17: Amériques Centrale et Antilles | C17: x | D17: NC | E17: NC | F17: NC | G17: NC | H17: NC | K17: 75 | L17: 0 | M17: Etranger | O17: AG
A18: ANTILLES NEERLANDAISES | B18: Amériques Centrale et Antilles | C18: x | D18: NC | E18: NC | F18: NC | G18: NC | H18: NC | K18: 75 | L18: 0 | M18: Etranger | O18: AN
A19: ARABIE SAOUDITE | B19: Afriq. Nord, P&M-Orient | C19: x | D19: 0.43 | E19: NC | F19: NC | G19: NC | H19: NC | K19: 77 | L19: 0 | M19: Etranger | O19: SA
A20: ARGENTINE | B20: Amériques du Sud | C20: x | D20: 0.34 | E20: NC | F20: NC | G20: NC | H20: NC | K20: 69 | L20: 0 | M20: Etranger | O20: AR
A21: ARMENIE | B21: Asie | C21: x | D21: NC | E21: NC | F21: NC | G21: NC | H21: NC | K21: 75 | L21: 0 | M21: Etranger | O21: AM
A22: ARUBA | D22: NC | E22: NC | F22: NC | G22: NC | H22: NC | K22: 0 | L22: 0 | M22: Etranger | O22: AW
A23: AUSTRALIE | B23: Pacifique Sud | C23: x | D23: 0.08 | E23: NC | F23: NC | G23: NC | H23: 0.07 | I23: 42.3 | K23: 210 | L23: 0 | M23: Etranger | O23: AU
A24: AUTRICHE | B24: Europe | C24: x | D24: 0 | E24: 0 | F24: 0 | G24: 0 | H24: 0 | K24: 110 | L24: 0 | M24: Etranger | O24: AT
A25: AZERBAIDJAN | B25: Europe | C25: x | D25: 0 | E25: 0 | F25: 0 | G25: 0 | H25: 0 | K25: 100 | L25: 0 | M25: Etranger | O25: AZ
A26: BAHAMAS | B26: Amériques Centrale et Antilles | D26: NC | E26: NC | F26: NC | G26: NC | H26: NC | K26: 0 | L26: 0 | M26: Etranger | O26: BS
A27: BAHREIN | B27: Afriq. Nord, P&M-Orient | C27: x | D27: NC | E27: NC | F27: NC | G27: NC | H27: NC | K27: 75 | L27: 0 | M27: Etranger | O27: BH
A28: BANGLADESH | B28: Asie | C28: x | D28: NC | E28: NC | F28: NC | G28: NC | H28: NC | K28: 75 | L28: 0 | M28: Etranger | O28: BD
A29: BARBADE | B29: Amériques Centrale et Antilles | C29: x | D29: NC | E29: NC | F29: NC | G29: NC | H29: NC | K29: 75 | L29: 0 | M29: Etranger | O29: BB
A30: BELARUS | B30: Europe | C30: x | D30: 0 | E30: 0 | F30: 0 | G30: 0 | H30: 0 | K30: 100 | L30: 0 | M30: Etranger | O30: BY
A31: BELGIQUE | B31: Europe | C31: x | D31: 0 | E31: 0 | F31: 0 | G31: 0 | H31: 0 | I31: 55.7 | K31: 100 | L31: 0 | M31: Etranger | O31: BE
A32: BELIZE | B32: Amériques Centrale et Antilles | C32: x | D32: NC | E32: NC | F32: NC | G32: NC | H32: NC | K32: 75 | L32: 0 | M32: Etranger | O32: BZ
A33: BENIN | B33: Afrique Francophone | C33: x | D33: 0.51 | E33: NC | F33: 0.53 | G33: NC | H33: NC | I33: 52.1 | K33: 78 | L33: 0 | M33: Etranger | O33: BJ
A34: BERMUDES | D34: NC | E34: NC | F34: NC | G34: NC | H34: NC | K34: 0 | L34: 0 | M34: Etranger | O34: BM
A35: BHOUTAN | B35: Asie | C35: x | D35: NC | E35: NC | F35: NC | G35: NC | H35: NC | K35: 75 | L35: 0 | M35: Etranger | O35: BT
A36: BOLIVIE | B36: Amériques du Sud | C36: x | D36: 0.46 | E36: NC | F36: NC | G36: NC | H36: NC | I36: 41.2 | K36: 63 | L36: 0 | M36: Etranger | O36: BO
A37: BOSNIE-HERZEGOVINE | B37: Europe | C37: x | D37: 0 | E37: 0 | F37: 0 | G37: 0 | H37: 0 | K37: 107 | L37: 0 | M37: Etranger | O37: BA
A38: BOTSWANA | B38: Afrique non Francophone | C38: x | D38: 0.37 | E38: NC | F38: NC | G38: NC | H38: NC | K38: 60 | L38: 0 | M38: Etranger | O38: BW
A39: BOUVET (île) | D39: NC | E39: NC | F39: NC | G39: NC | H39: NC | K39: 0 | L39: 0 | M39: Etranger | O39: BV
A40: BRESIL | B40: Amériques du Sud | C40: x | D40: 0.39 | E40: NC | F40: 0.36 | G40: NC | H40: NC | I40: 52.4 | K40: 93 | L40: 0 | M40: Etranger | O40: BR
A41: BRUNEI | B41: Asie | C41: x | D41: NC | E41: NC | F41: NC | G41: NC | H41: NC | K41: 75 | L41: 0 | M41: Etranger | O41: BN
A42: BULGARIE | B42: Europe | C42: x | D42: 0 | E42: 0 | F42: 0 | G42: 0 | H42: 0 | K42: 100 | L42: 0 | M42: Etranger | O42: BG
A43: BURKINA FASO | B43: Afrique Francophone | C43: x | D43: 0.63 | E43: NC | F43: NC | G43: NC | H43: NC | I43: 47.8 | K43: 70 | L43: 0 | M43: Etranger | O43: BF
A44: BURUNDI | B44: Afrique Francophone | C44: x | D44: 0.62 | E44: NC | F44: NC | G44: NC | H44: NC | K44: 75 | L44: 0 | M44: Etranger | O44: BI
A45: CAIMANES (îles) | D45: NC | E45: NC | F45: NC | G45: NC | H45: NC | K45: 0 | L45: 0 | M45: Etranger | O45: KY
A46: CAMBODGE | B46: Asie | C46: x | D46: 0.47 | E46: NC | F46: NC | G46: NC | H46: NC | I46: 54.3 | K46: 75 | L46: 0 | M46: Etranger | O46: KH
A47: CAMEROUN | B47: Afrique Francophone | C47: x | D47: 0.58 | E47: NC | F47: 0.59 | G47: NC | H47: NC | K47: 79 | L47: 0 | M47: Etranger | O47: CM
A48: CANADA | B48: Amériques du Nord | C48: x | D48: 0.1 | E48: NC | F48: NC | G48: NC | H48: NC | I48: 41.2 | K48: 81 | L48: 0 | M48: Etranger | O48: CA
A49: CANARIES(iles) | B49: Afriq. Nord, P&M-Orient | C49: x | D49: NC | E49: NC | F49: NC | G49: NC | H49: NC | K49: 75 | L49: 0 | M49: Etranger | O49: ES
A50: CAP-VERT | B50: Afrique non Francophone | C50: x | D50: NC | E50: NC | F50: NC | G50: NC | H50: NC | K50: 75 | L50: 0 | M50: Etranger | O50: CV
A51: CHILI | B51: Amériques du Sud | C51: x | D51: NC | E51: NC | F51: NC | G51: NC | H51: NC | K51: 74 | L51: 0 | M51: Etranger | O51: CL
A52: CHINE | B52: Asie | C52: x | D52: 0.43 | E52: NC | F52: NC | G52: NC | H52: NC | K52: 99 | L52: 0 | M52: Etranger | O52: CN
A53: CHRISTMAS (île) | D53: NC | E53: NC | F53: NC | G53: NC | H53: NC | K53: 0 | L53: 0 | M53: Etranger | O53: CX
A54: CHYPRE | B54: Europe | C54: x | D54: 0 | E54: 0 | F54: 0 | G54: 0 | H54: 0 | K54: 100 | L54: 0 | M54: Etranger | O54: CY
A55: COCOS (îles) | D55: NC | E55: NC | F55: NC | G55: NC | H55: NC | K55: 0 | L55: 0 | M55: Etranger | O55: CC
A56: COLOMBIE | B56: Amériques du Sud | C56: x | D56: 0.52 | E56: NC | F56: 0.49 | G56: NC | H56: NC | I56: 41.8 | K56: 79 | L56: 0 | M56: Etranger | O56: CO
A57: COMORES | B57: Océan indien | C57: x | D57: 0.53 | E57: NC | F57: NC | G57: NC | H57: 0.5 | K57: 75 | L57: 0 | M57: Etranger | O57: KM
A58: CONGO(Brazzaville/Pointe Noire) | B58: Afrique Francophone | C58: x | D58: 0.52 | E58: NC | F58: NC | G58: NC | H58: NC | I58: 63.8 | K58: 165 | L58: 0 | M58: Etranger | O58: CG
A59: COOK (îles) | B59: Pacifique Sud | C59: x | D59: NC | E59: NC | F59: NC | G59: NC | H59: NC | K59: 75 | L59: 0 | M59: Etranger | O59: CK
A60: COREE du sud(République) | B60: Asie | C60: x | D60: NC | E60: NC | F60: NC | G60: NC | H60: NC | K60: 81 | L60: 0 | M60: Etranger | O60: KR
A61: COREE (République Populaire) | D61: NC | E61: NC | F61: NC | G61: NC | H61: NC | K61: 0 | L61: 0 | M61: Etranger | O61: KP
A62: COSTA RICA | B62: Amériques Centrale et Antilles | C62: x | D62: 0.35 | E62: 0.32 | F62: 0.32 | G62: NC | H62: NC | I62: 52.1 | K62: 91 | L62: 0 | M62: Etranger | O62: CR
A63: COTE D'IVOIRE | B63: Afrique Francophone | C63: x | D63: 0.54 | E63: NC | F63: 0.56 | G63: NC | H63: NC | I63: 59 | K63: 87 | L63: 0 | M63: Etranger | O63: CI
A64: CROATIE | B64: Europe | C64: x | D64: 0 | E64: 0 | F64: 0 | G64: 0 | H64: 0 | K64: 100 | L64: 0 | M64: Etranger | O64: HR
A65: CUBA | B65: Amériques Centrale et Antilles | C65: x | D65: 0.37 | E65: 0.35 | F65: 0.34 | G65: NC | H65: NC | K65: 63 | L65: 0 | M65: Etranger | O65: CU
A66: DANEMARK | B66: Europe | C66: x | D66: 0 | E66: 0 | F66: 0 | G66: 0 | H66: 0 | K66: 105 | L66: 0 | M66: Etranger | O66: DK
A67: DJIBOUTI | B67: Afrique Francophone | C67: x | D67: 0.52 | E67: NC | F67: NC | G67: NC | H67: NC | K67: 75 | L67: 0 | M67: Etranger | O67: DJ
A68: DOMINICAINE (République) | B68: Amériques Centrale et Antilles | C68: x | D68: 0.4 | E68: NC | F68: 0.36 | G68: NC | H68: NC | I68: 49.7 | K68: 67 | L68: 0 | M68: Etranger | O68: DO
A69: DOMINIQUE | B69: Amériques Centrale et Antilles | C69: x | D69: NC | E69: 0.36 | F69: 0.36 | G69: NC | H69: NC | K69: 75 | L69: 0 | M69: Etranger | O69: DM
A70: EGYPTE | B70: Afriq. Nord, P&M-Orient | C70: x | D70: NC | E70: NC | F70: NC | G70: NC | H70: NC | K70: 73 | L70: 0 | M70: Etranger | O70: EG
A71: EMIRATS ARABES UNIS | B71: Afriq. Nord, P&M-Orient | C71: x | D71: 0.32 | E71: NC | F71: NC | G71: NC | H71: NC | K71: 75 | L71: 0 | M71: Etranger | O71: AE
A72: EQUATEUR | B72: Amériques du Sud | C72: x | D72: 0.41 | E72: NC | F72: NC | G72: NC | H72: NC | K72: 69 | L72: 0 | M72: Etranger | O72: EC
A73: ERYTHREE | B73: Afrique non Francophone | C73: x | D73: NC | E73: NC | F73: NC | G73: NC | H73: NC | K73: 75 | L73: 0 | M73: Etranger | O73: ER
A74: ESPAGNE | B74: Europe | C74: x | D74: 0 | E74: 0 | F74: 0 | G74: 0 | H74: 0 | I74: 42.7 | K74: 90 | L74: 0 | M74: Etranger | O74: ES
A75: ESTONIE | B75: Europe | C75: x | D75: 0 | E75: 0 | F75: 0 | G75: 0 | H75: 0 | K75: 100 | L75: 0 | M75: Etranger | O75: EE
A76: ETATS-UNIS (Washington, San Fransisco) | B76: Amériques du Nord | C76: x | D76: 0.18 | E76: 0.19 | F76: 0.16 | G76: NC | H76: NC | I76: 49.2 | K76: 60 | L76: 0 | M76: Etranger | O76: US
A77: ETATS-UNIS (Miami) | B77: Amériques du Nord | C77: x | D77: 0.21 | E77: 0.19 | F77: 0.18 | G77: NC | H77: NC | I77: 49.2 | K77: 60 | L77: 0 | M77: Etranger | O77: US
A78: ETHIOPIE | B78: Afrique non Francophone | C78: x | D78: 0.61 | E78: NC | F78: NC | G78: NC | H78: NC | I78: 65.3 | K78: 72 | L78: 0 | M78: Etranger | O78: ET
A79: FALKLAND (îles) | D79: NC | E79: NC | F79: NC | G79: NC | H79: NC | K79: 0 | L79: 0 | M79: Etranger | O79: FK
A80: FEROE (îles) | D80: NC | E80: NC | F80: NC | G80: NC | H80: NC | K80: 0 | L80: 0 | M80: Etranger | O80: FO
A81: FIDJI | B81: Pacifique Sud | C81: x | D81: NC | E81: NC | F81: NC | G81: NC | H81: NC | K81: 75 | L81: 0 | M81: Etranger | O81: FJ
A82: FINLANDE | B82: Europe | C82: x | D82: 0 | E82: 0 | F82: 0 | G82: 0 | H82: 0 | K82: 100 | L82: 0 | M82: Etranger | O82: FI
A83: GABON | B83: Afrique Francophone | C83: x | D83: 0.44 | E83: NC | F83: NC | G83: NC | H83: NC | K83: 146 | L83: 0 | M83: Etranger | O83: GA
A84: GAMBIE | B84: Afrique non Francophone | C84: x | D84: NC | E84: NC | F84: NC | G84: NC | H84: NC | K84: 69 | L84: 0 | M84: Etranger | O84: GM
A85: GEORGIE | B85: Asie | C85: x | D85: NC | E85: NC | F85: NC | G85: NC | H85: NC | K85: 75 | L85: 0 | M85: Etranger | O85: GE
A86: GEORGIE - ILES SANDWICH DU SUD | D86: NC | E86: NC | F86: NC | G86: NC | H86: NC | K86: 0 | L86: 0 | M86: Etranger | O86: GS
A87: GHANA | B87: Afrique non Francophone | C87: x | D87: 0.42 | E87: NC | F87: 0.43 | G87: NC | H87: 0.43 | K87: 62 | L87: 0 | M87: Etranger | O87: GH
A88: GIBRALTAR | B88: Europe | D88: 0 | E88: 0 | F88: 0 | G88: 0 | H88: 0 | K88: 0 | L88: 0 | M88: Etranger | O88: GI
A89: GRECE | B89: Europe | C89: x | D89: 0 | E89: 0 | F89: 0 | G89: 0 | H89: 0 | K89: 100 | L89: 0 | M89: Etranger | O89: GR
A90: GRENADE | B90: Amériques Centrale et Antilles | C90: x | D90: NC | E90: NC | F90: NC | G90: NC | H90: NC | K90: 75 | L90: 0 | M90: Etranger | O90: GD
A91: GROENLAND | D91: NC | E91: NC | F91: NC | G91: NC | H91: NC | K91: 0 | L91: 0 | M91: Etranger | O91: GL
A92: GUAM | D92: NC | E92: NC | F92: NC | G92: NC | H92: NC | K92: 0 | L92: 0 | M92: Etranger | O92: GU
A93: GUATEMALA | B93: Amériques Centrale et Antilles | C93: x | D93: 0.5 | E93: NC | F93: NC | G93: NC | H93: NC | K93: 87 | L93: 0 | M93: Etranger | O93: GT
A94: GUINEE(conakry) | B94: Afrique Francophone | C94: x | D94: 0.57 | E94: NC | F94: NC | G94: NC | H94: NC | I94: 61 | J94: 82.9 | K94: 75 | L94: 0 | M94: Etranger | O94: GN
A95: GUINEE EQUATORIALE(Malabo) | B95: Afrique non Francophone | C95: x | D95: NC | E95: NC | F95: NC | G95: NC | H95: NC | K95: 71 | L95: 0 | M95: Etranger | O95: GQ
A96: GUINEE-BISSAU | B96: Afrique non Francophone | C96: x | D96: NC | E96: NC | F96: NC | G96: NC | H96: NC | K96: 75 | L96: 0 | M96: Etranger | O96: GW
A97: GUYANA | B97: Amériques du Sud | C97: x | D97: NC | E97: NC | F97: NC | G97: NC | H97: NC | K97: 75 | L97: 0 | M97: Etranger | O97: GY
A98: HAITI | B98: Amériques Centrale et Antilles | C98: x | D98: 0.65 | E98: NC | F98: 0.6 | G98: NC | H98: NC | I98: 48.1 | K98: 75 | L98: 0 | M98: Etranger | O98: HT
A99: HAWAI (Etats-Unis) | B99: Pacifique Sud | C99: x | D99: NC | E99: NC | F99: NC | G99: NC | H99: NC | K99: 75 | L99: 0 | M99: Etranger | O99: US
A100: HEARD ET MC DONALD (îles) | D100: NC | E100: NC | F100: NC | G100: NC | H100: NC | K100: 0 | L100: 0 | M100: Etranger | O100: HM
...

Sheet Organisation
A1: UNITES | B1: Code SIRH | C1: Libellé | D1: Département | E1: Commentaire sur fusion ou disparition d'UR/Service
A2: =$B2&"-"&$C2 -> A0017-UMR INTERTRYP | B2: A0017 | C2: UMR INTERTRYP | D2: Bios
A3: =$B3&"-"&$C3 -> A0051-UMR AMAP | B3: A0051 | C3: UMR AMAP | D3: Bios
A4: =$B4&"-"&$C4 -> A0053-UMR PVBMT | B4: A0053 | C4: UMR PVBMT | D4: Bios
A5: =$B5&"-"&$C5 -> A0055-UMR CBGP | B5: A0055 | C5: UMR CBGP | D5: Bios
A6: =$B6&"-"&$C6 -> A0082-UMR LSTM | B6: A0082 | C6: UMR LSTM | D6: Bios
A7: =$B7&"-"&$C7 -> A0100-UMR DIADE | B7: A0100 | C7: UMR DIADE | D7: Bios
A8: =$B8&"-"&$C8 -> A0108-UMR AGAP | B8: A0108 | C8: UMR AGAP | D8: Bios
A9: =$B9&"-"&$C9 -> A0117-UMR ASTRE | B9: A0117 | C9: UMR ASTRE | D9: Bios
A10: =$B10&"-"&$C10 -> A0120-UMR PHIM | B10: A0120 | C10: UMR PHIM | D10: Bios
A11: =$B11&"-"&$C11 -> B0026-UPR GECO | B11: B0026 | C11: UPR GECO | D11: Persyst
A12: =$B12&"-"&$C12 -> B0049-US Analyses | B12: B0049 | C12: US Analyses | D12: Persyst
A13: =$B13&"-"&$C13 -> B0078-UPR Recyclage et risque | B13: B0078 | C13: UPR Recyclage et risque | D13: Persyst
... A47: =$B47&"-"&$C47 -> D2962-Dgdrs-Dims | B47: D2962 | C47: Dgdrs-Dims | D47: Dg

Sheet autres ldv
A1: Congés ODM ligne 26 | D1: Congés NDF
A2: 1er période | B2: =IF(ODM!D25="",0,(ODM!G25-ODM!D25)+1) -> 2 | D2: =IF(NDF!E22="",0,(NDF!H22-NDF!E22)+1) -> 2
A3: 2eme periode | B3: =IF(ODM!J25="",0,(ODM!M25-ODM!J25)+1) -> 0 | D3: =IF(NDF!K22="",0,(NDF!N22-NDF!K22)+1) -> 0
A5: Autres frais de transport
A6: Taxi, bus, metro
A7: Train, avion, bateau
A8: location véhicule
A9: Carburant, péages, parking
A10: Autres
S14: =IF(D14="","",IF($F$7<>$L$7,0,IF($D14=$F$7,0,IF(VLOOKUP($AB$5,'autres ldv'!I48:K55,3,FALSE)="Non",0,VLOOKUP($D14,Pays!$A$1:$M$261,VLOOKUP($P$11,Pays!$A$1:$N$6,14,FALSE),FALSE)))))
A15: Oui
A16: Non
A18: Véhicule
A19: Auto | B19: 1
A20: Moto > = 125 cc | B20: 0.5
A21: Moto < 125 cc | B21: 0.25 | D21: Attention, inf car sinon formule ne fonctionne pas.
A23: Forfait terrain étranger
A24: Repas | B24: 22
A25: nuitées | B25: 41
A26: 1 jour
A27: Forfait France
A28: Plafond nuitée & dej Ile de France (PI) | B28: 135
A29: Plafond nuitée & dej Province (PP) | B29: 105
A30: Forfait Urssaf nuitée & dej Ile de France (FI) | B30: 74.3
A31: Forfait Urssaf nuitée & dej Province (FP) | B31: 55.1
A32: Forfait repas (FR) | B32: 20.7
A34: Taux de charge IS : | B34: 0.49
A36: Montant moyen mensuel IS
A37: Indice moyen | B37: 670 | D37: Nouvel indice suite convention unique
A38: Valeur du point | B38: 6.5
A39: Allocation brute métropole | B39: 2044.12
A40: Allocation brute Dom | B40: 2196
A42: Montant moyen mensuel IS
A43: Indice moyen | B43: 670
A44: Valeur du point | B44: 6.5
A45: Allocation brute métropole | B45: 2044.12 | C45: ALLR | D45: pour date début contrat >= 01/09/2021
A46: Allocation brute Dom | B46: 2196 | C46: ALLR | D46: pour date début contrat >= 01/09/2021
I47: Contrat | J47: Libellé | K47: IS | L47: Commentaire | M47: Type | N47: Type RH
I48: CDI | J48: CDI | K48: Oui | M48: CDI | N48: 143
I49: CDD | J49: CDD (sauf doctorant et post doc) | K49: Oui | L49: Oui si mission à la demande du Cirad | M49: CDD | N49: 165
I50: APR | J50: Apprenti | K50: Non | M50: APR | N50: 165
I51: CPRO | J51: Contrat professionnalisation | K51: Non | M51: CPRO | N51: 165
I52: ALLR | J52: Doctorant Cirad | K52: Oui | M52: ALLR | N52: 200
I53: VI | J53: Volontaires en entreprise | K53: Non | M53: VI | N53: 175
I54: VSC | J54: Détaché externe Cirad | K54: Non | L54: Non (Ciradiens détachés dans autres organismes) | M54: VSC | N54: 199
I55: PDOC | J55: Post doc | K55: Oui | M55: PDOC | N55: 178

Sheet Liste Structure
A1: COD_SEGMENT | B1: LIB_LONG_SEGMENT | C1: Concaténation | D1: COD_SEGMENT | H1: Unité | I1: Dpt
A2: A01700 | B2: INTERTRYP | C2: =A2&"-"&B2 -> A01700-INTERTRYP | D2: =A2 -> A01700 | H2: A | I2: Bios
A3: A05100 | B3: AMAP | C3: =A3&"-"&B3 -> A05100-AMAP | D3: =A3 -> A05100 | H3: B | I3: Persyst
A4: A05300 | B4: PVBMT | C4: =A4&"-"&B4 -> A05300-PVBMT | D4: =A4 -> A05300 | H4: C | I4: Es
A5: A05500 | B5: CBGP | C5: =A5&"-"&B5 -> A05500-CBGP | D5: =A5 -> A05500 | H5: D | I5: Dg
A6: A10000 | B6: DIADE | C6: =A6&"-"&B6 -> A10000-DIADE | D6: =A6 -> A10000
A7: A10800 | B7: AGAP - Management - Animation | C7: =A7&"-"&B7 -> A10800-AGAP - Management - Animation | D7: =A7 -> A10800
A8: A10802 | B8: AGAP - AFEF | C8: =A8&"-"&B8 -> A10802-AGAP - AFEF | D8: =A8 -> A10802
A9: A10803 | B9: AGAP - BISSAPP | C9: =A9&"-"&B9 -> A10803-AGAP - BISSAPP | D9: =A9 -> A10803
A10: A10804 | B10: AGAP - DARS | C10: =A10&"-"&B10 -> A10804-AGAP - DARS | D10: =A10 -> A10804
A11: A10805 | B11: AGAP - DAAV | C11: =A11&"-"&B11 -> A10805-AGAP - DAAV | D11: =A11 -> A10805
A12: A10806 | B12: AGAP - DDSE | C12: =A12&"-"&B12 -> A10806-AGAP - DDSE | D12: =A12 -> A10806
A13: A10807 | B13: AGAP - GIV | C13: =A13&"-"&B13 -> A10807-AGAP - GIV | D13: =A13 -> A10807
A14: A10808 | B14: AGAP - GSP | C14: =A14&"-"&B14 -> A10808-AGAP - GSP | D14: =A14 -> A10808
A15: A10809 | B15: AGAP - GE²pop | C15: =A15&"-"&B15 -> A10809-AGAP - GE²pop | D15: =A15 -> A10809
A16: A10812 | B16: AGAP - SEG | C16: =A16&"-"&B16 -> A10812-AGAP - SEG | D16: =A16 -> A10812
A17: A10817 | B17: AGAP - GABA | C17: =A17&"-"&B17 -> A10817-AGAP - GABA | D17: =A17 -> A10817
... A128: D98504 | B128: PDG - DAffaires publiques | C128: =A128&"-"&B128 -> D98504-PDG - DAffaires publiques | D128: =A128 -> D98504
A129: 900000 | B129: Structure technique | C129: =A129&"-"&B129 -> 900000-Structure technique | D129: =A129 -> 900000

Sheet Liste Activites
A1: COD_SEGMENT | B1: LIB_LONG_SEGMENT | C1: Concaténation | D1: COD_SEGMENT
A2: A01T001 | B2: Fonctionnement Direction, management, appui | C2: =A2&"-"&B2 -> A01T001-Fonctionnement Direction, management, appui | D2: A01T001
A3: A01T002 | B3: Comitologie | C3: =A3&"-"&B3 -> A01T002-Comitologie | D3: A01T002
A4: A01T003 | B4: Animation scientifique | C4: =A4&"-"&B4 -> A01T003-Animation scientifique | D4: A01T003
A5: A01T004 | B5: Fonctionnement opérationnel | C5: =A5&"-"&B5 -> A01T004-Fonctionnement opérationnel | D5: A01T004
A6: A02T001 | B6: Soutien aux doctorants | C6: =A6&"-"&B6 -> A02T001-Soutien aux doctorants | D6: A02T001
A7: A02T002 | B7: Soutien aux DP | C7: =A7&"-"&B7 -> A02T002-Soutien aux DP | D7: A02T002
A8: A02T003 | B8: CRESi | C8: =A8&"-"&B8 -> A02T003-CRESi | D8: A02T003
A9: A02T004 | B9: ProPIS | C9: =A9&"-"&B9 -> A02T004-ProPIS | D9: A02T004
A10: A02T005 | B10: Actions de valorisation | C10: =A10&"-"&B10 -> A02T005-Actions de valorisation | D10: A02T005
A11: A02T006 | B11: Renforcement compétences chercheurs du Sud | C11: =A11&"-"&B11 -> A02T006-Renforcement compétences chercheurs du Sud | D11: A02T006
A12: A02T007 | B12: Formation collectives au Sud | C12: =A12&"-"&B12 -> A02T007-Formation collectives au Sud | D12: A02T007
A13: A02T008 | B13: Equipements scientifiques | C13: =A13&"-"&B13 -> A02T008-Equipements scientifiques | D13: A02T008
... A113: A99T021 | B113: Autres dossiers spécifiques DCAF | C113: =A113&"-"&B113 -> A99T021-Autres dossiers spécifiques DCAF | D113: A99T021

Sheet Liste Géo
A1: COD_SEGMENT | B1: LIB_LONG_SEGMENT | C1: Concaténation | D1: COD_SEGMENT
A2: AD | B2: Andorre | C2: =A2&"-"&B2 -> AD-Andorre | D2: AD
A3: AE | B3: Émirats arabes unis | C3: =A3&"-"&B3 -> AE-Émirats arabes unis | D3: AE
A4: AF | B4: Afghanistan | C4: =A4&"-"&B4 -> AF-Afghanistan | D4: AF
A5: AG | B5: Antigua-et-Barbuda | C5: =A5&"-"&B5 -> AG-Antigua-et-Barbuda | D5: AG
A6: AI | B6: Anguilla | C6: =A6&"-"&B6 -> AI-Anguilla | D6: AI
A7: AL | B7: Albanie | C7: =A7&"-"&B7 -> AL-Albanie | D7: AL
A8: AM | B8: Arménie | C8: =A8&"-"&B8 -> AM-Arménie | D8: AM
A9: AN | B9: Antilles néerlandaises | C9: =A9&"-"&B9 -> AN-Antilles néerlandaises | D9: AN
A10: AO | B10: Angola | C10: =A10&"-"&B10 -> AO-Angola | D10: AO
A11: AQ | B11: Antarctique | C11: =A11&"-"&B11 -> AQ-Antarctique | D11: AQ
A12: AR | B12: Argentine | C12: =A12&"-"&B12 -> AR-Argentine | D12: AR
A13: AS | B13: Samoa américaines | C13: =A13&"-"&B13 -> AS-Samoa américaines | D13: AS
... A254: ZW | B254: Zimbabwe | C254: =A254&"-"&B254 -> ZW-Zimbabwe | D254: ZW
